{
    "description": "You are given an array of exactly $ n $ numbers $ [1,2,3,\\ldots,n] $ along with integers $ k $ and $ x $ .\n\nPartition the array in exactly $ k $ non-empty disjoint subsequences such that the [bitwise XOR](https://en.wikipedia.org/wiki/Bitwise_operation#XOR) of all numbers in each subsequence is $ x $ , and each number is in exactly one subsequence. Notice that there are no constraints on the length of each subsequence.\n\nA sequence $ a $ is a subsequence of a sequence $ b $ if $ a $ can be obtained from $ b $ by the deletion of several (possibly, zero or all) elements.\n\nFor example, for $ n = 15 $ , $ k = 6 $ , $ x = 7 $ , the following scheme is valid:\n\n- $ [6,10,11] $ , $ 6 \\oplus 10 \\oplus 11 = 7 $ ,\n- $ [5,12,14] $ , $ 5 \\oplus 12 \\oplus 14 = 7 $ ,\n- $ [3,9,13] $ , $ 3 \\oplus 9 \\oplus 13 = 7 $ ,\n- $ [1,2,4] $ , $ 1 \\oplus 2 \\oplus 4 = 7 $ ,\n- $ [8,15] $ , $ 8 \\oplus 15 = 7 $ ,\n- $ [7] $ , $ 7 = 7 $ ,\n\n where $ \\oplus $ represents the bitwise XOR operation.The following scheme is invalid, since $ 8 $ , $ 15 $ do not appear:\n\n- $ [6,10,11] $ , $ 6 \\oplus 10 \\oplus 11 = 7 $ ,\n- $ [5,12,14] $ , $ 5 \\oplus 12 \\oplus 14 = 7 $ ,\n- $ [3,9,13] $ , $ 3 \\oplus 9 \\oplus 13 = 7 $ ,\n- $ [1,2,4] $ , $ 1 \\oplus 2 \\oplus 4 = 7 $ ,\n- $ [7] $ , $ 7 = 7 $ .\n\nThe following scheme is invalid, since $ 3 $ appears twice, and $ 1 $ , $ 2 $ do not appear:\n\n- $ [6,10,11] $ , $ 6 \\oplus 10 \\oplus 11 = 7 $ ,\n- $ [5,12,14] $ , $ 5 \\oplus 12 \\oplus 14 = 7 $ ,\n- $ [3,9,13] $ , $ 3 \\oplus 9 \\oplus 13 = 7 $ ,\n- $ [3,4] $ , $ 3 \\oplus 4 = 7 $ ,\n- $ [8,15] $ , $ 8 \\oplus 15 = 7 $ ,\n- $ [7] $ , $ 7 = 7 $ .",
    "inputFormat": "Each test contains multiple test cases. The first line contains an integer $ t $ ( $ 1 \\le t \\le 10^4 $ ) \u2014 the number of test cases.\n\nThe first and the only line of each test case contains three integers $ n $ , $ k $ , $ x $ ( $ 1 \\le k \\le n \\le 2 \\cdot 10^5 $ ; $ 1\\le x \\le 10^9 $ ) \u2014 the length of the array, the number of subsequences and the required XOR.\n\nIt's guaranteed that the sum of $ n $ does not exceed $ 2 \\cdot 10^5 $ .",
    "outputFormat": "For each test case, if it is possible to partition the sequence, print \"YES\" in the first line. In the $ i $ -th of the following $ k $ lines first print the length $ s_i $ of the $ i $ -th subsequence, then print $ s_i $ integers, representing the elements in the $ i $ -th subsequence. If there are multiple answers, print any. Note that you can print a subsequence in any order.\n\nIf it is not possible to partition the sequence, print \"NO\".",
    "samples": [
        [
            "7\n15 6 7\n11 4 5\n5 3 2\n4 1 4\n6 1 7\n11 5 5\n11 6 5",
            "YES\n3 6 10 11\n3 5 12 14\n3 3 9 13\n3 1 2 4\n2 8 15\n1 7\nYES\n2 1 4\n2 2 7\n2 3 6\n5 5 8 9 10 11\nNO\nYES\n4 1 2 3 4\nYES\n6 1 2 3 4 5 6\nNO\nNO"
        ]
    ],
    "hint": "In the first test case, we construct the following $ 6 $ subsequences:\n\n- $ [6,10,11] $ , $ 6 \\oplus 10 \\oplus 11 = 7 $ ,\n- $ [5,12,14] $ , $ 5 \\oplus 12 \\oplus 14 = 7 $ ,\n- $ [3,9,13] $ , $ 3 \\oplus 9 \\oplus 13 = 7 $ ,\n- $ [1,2,4] $ , $ 1 \\oplus 2 \\oplus 4 = 7 $ ,\n- $ [8,15] $ , $ 8 \\oplus 15 = 7 $ ,\n- $ [7] $ , $ 7 = 7 $ .\n\nIn the second test case, we construct the following $ 4 $ subsequences:\n\n- $ [1,4] $ , $ 1 \\oplus 4 = 5 $ ,\n- $ [2,7] $ , $ 2 \\oplus 7 = 5 $ ,\n- $ [3,6] $ , $ 3 \\oplus 6 = 5 $ ,\n- $ [5,8,9,10,11] $ , $ 5 \\oplus 8 \\oplus 9 \\oplus 10 \\oplus 11 = 5 $ .\n\nThe following solution is considered correct in this test case as well:\n\n- $ [1,4] $ , $ 1 \\oplus 4 = 5 $ ,\n- $ [2,7] $ , $ 2 \\oplus 7 = 5 $ ,\n- $ [5] $ , $ 5 = 5 $ ,\n- $ [3,6,8,9,10,11] $ , $ 3 \\oplus 6 \\oplus 8 \\oplus 9 \\oplus 10 \\oplus 11 = 5 $ .",
    "translation": "### \u9898\u76ee\u63cf\u8ff0\n\n\u7ed9\u5b9a $n$ \u4e2a\u6570 $[1,2,3,\\ldots,n]$ \u548c\u4e24\u4e2a\u6b63\u6574\u6570 $k$ \u548c $x$\u3002\n\n\u5c06\u8fd9\u4e9b\u6570\u5206\u6210\u6070\u597d $k$ \u7ec4\u4f7f\u5f97\u6bcf\u7ec4\u7684\u5f02\u6216\u548c\u90fd\u662f $x$\u3002\u5177\u4f53\u5730\uff0c\u6bcf\u4e2a\u6570\u90fd\u5fc5\u987b\u51fa\u73b0\u5728\u6070\u597d\u4e00\u7ec4\u5185\u3002\n\n\u4f8b\u5982\uff0c$n = 15,k = 6,x = 7$ \u65f6\uff0c\u4e0b\u5217\u5206\u6cd5\u662f\u5408\u6cd5\u7684\uff08$\\oplus$ \u8868\u793a\u6309\u4f4d\u5f02\u6216\u8fd0\u7b97\uff09\uff1a\n\n- $[6,10,11]$, $6 \\oplus 10 \\oplus 11 = 7$\n- $[5,12,14]$, $5 \\oplus 12 \\oplus 14 = 7$\n- $[3,9,13]$, $3 \\oplus 9 \\oplus 13 = 7$\n- $[1,2,4]$, $1 \\oplus 2 \\oplus 4 = 7$\n- $[8,15]$, $8 \\oplus 15 = 7$\n- $[7]$, $7 = 7$\n\n\u4e0b\u5217\u5206\u6cd5\u662f\u4e0d\u5408\u6cd5\u7684\uff1a\n\n- $[6,10,11]$, $6 \\oplus 10 \\oplus 11 = 7$\n- $[5,12,14]$, $5 \\oplus 12 \\oplus 14 = 7$\n- $[3,9,13]$, $3 \\oplus 9 \\oplus 13 = 7$\n- $[1,2,4]$, $1 \\oplus 2 \\oplus 4 = 7$\n- $[7]$, $7 = 7$\n\n\u56e0\u4e3a $8$ \u548c $15$ \u6ca1\u6709\u51fa\u73b0\u3002\n\n\u4e0b\u5217\u5206\u6cd5\u4e5f\u4e0d\u5408\u6cd5\uff1a\n\n- $[6,10,11]$, $6 \\oplus 10 \\oplus 11 = 7$,\n- $[5,12,14]$, $5 \\oplus 12 \\oplus 14 = 7$,\n- $[3,9,13]$, $3 \\oplus 9 \\oplus 13 = 7$,\n- $[3,4]$, $3 \\oplus 4 = 7$,\n- $[8,15]$, $8 \\oplus 15 = 7$,\n- $[7]$, $7 = 7$.\n\n\u56e0\u4e3a $1$ \u548c $2$ \u672a\u51fa\u73b0\u4e14 $3$ \u51fa\u73b0\u4e24\u6b21\u3002\n\n~~\u8fd9\u9898\u672c\u6765\u662f C~~\n\n### \u8f93\u5165\u683c\u5f0f\n\n\u7b2c\u4e00\u884c\u4e00\u4e2a\u6b63\u6574\u6570 $t$\uff08$1\\le t\\le 10^4$\uff09\u8868\u793a\u6d4b\u8bd5\u6570\u636e\u7ec4\u6570\u3002\n\n\u6bcf\u7ec4\u6d4b\u8bd5\u6570\u636e\u4e00\u884c\u4e09\u4e2a\u6b63\u6574\u6570 $n,k,x$\uff08$1 \\le k \\le n \\le 2 \\cdot 10^5$\uff0c$1\\le x \\le 10^9$\uff09\uff0c\u542b\u4e49\u89c1\u9898\u76ee\u63cf\u8ff0\u3002\n\n\u4fdd\u8bc1\u6240\u6709\u6d4b\u8bd5\u6570\u636e\u7684 $n$ \u4e4b\u548c\u4e0d\u8d85\u8fc7 $2\\cdot 10^5$\u3002\n\n### \u8f93\u51fa\u683c\u5f0f\n\n\u5bf9\u4e8e\u6bcf\u7ec4\u6d4b\u8bd5\u6570\u636e\uff0c\u82e5\u4e0d\u5b58\u5728\u5408\u6cd5\u65b9\u6848\uff0c\u8f93\u51fa `NO`\u3002\u82e5\u5b58\u5728\uff0c\u5148\u8f93\u51fa `YES`\uff0c\u63a5\u4e0b\u6765 $k$ \u884c\u8f93\u51fa\u65b9\u6848\u3002\u5177\u4f53\u5730\uff0c\u6bcf\u4e00\u884c\u7b2c\u4e00\u4e2a\u6570\u5b57\u8f93\u51fa\u8fd9\u4e00\u7ec4\u7684\u957f\u5ea6 $s_i$\uff0c\u540e\u63a5 $s_i$ \u4e2a\u6570\u5b57\u8868\u793a\u8fd9\u4e00\u7ec4\u7684\u6570\u5b57\u3002\u6ce8\u610f\u6bcf\u4e00\u7ec4\u4e2d\u7684\u6570\u5b57\u53ef\u4ee5\u6309\u4efb\u610f\u987a\u5e8f\u7ed9\u51fa\u3002\n\n### \u6837\u4f8b\u89e3\u91ca\n\n\u7b2c\u4e00\u7ec4\u6d4b\u8bd5\u6570\u636e\u4e2d\uff0c\u7ed9\u51fa\u7684\u4e00\u7ec4\u5408\u6cd5\u65b9\u6848\u5982\u4e0b\uff1a\n\n- $[6,10,11]$, $6 \\oplus 10 \\oplus 11 = 7$\n- $[5,12,14]$, $5 \\oplus 12 \\oplus 14 = 7$\n- $[3,9,13]$, $3 \\oplus 9 \\oplus 13 = 7$\n- $[1,2,4]$, $1 \\oplus 2 \\oplus 4 = 7$\n- $[8,15]$, $8 \\oplus 15 = 7$\n- $[7]$, $7 = 7$\n\n\u7b2c\u4e8c\u7ec4\u6d4b\u8bd5\u6570\u636e\u4e2d\uff0c\u7ed9\u51fa\u7684\u4e00\u7ec4\u5408\u6cd5\u65b9\u6848\u5982\u4e0b\uff1a\n\n- $[1,4]$, $1 \\oplus 4 = 5$\n- $[2,7]$, $2 \\oplus 7 = 5$\n- $[3,6]$, $3 \\oplus 6 = 5$\n- $[5,8,9,10,11]$, $5 \\oplus 8 \\oplus 9 \\oplus 10 \\oplus 11 = 5$\n\n\u540c\u65f6\u4e0b\u9762\u7684\u65b9\u6848\u4e5f\u5408\u6cd5\uff1a\n\n- $[1,4]$, $1 \\oplus 4 = 5$\n- $[2,7]$, $2 \\oplus 7 = 5$\n- $[5]$, $5 = 5$\n- $[3,6,8,9,10,11]$, $3 \\oplus 6 \\oplus 8 \\oplus 9 \\oplus 10 \\oplus 11 = 5$"
}