{
    "description": "This task is very simple. Given a string $ S $ of length $ n $ and $ q $ queries each query is on the format $ i $ $ j $ $ k $ which means sort the substring consisting of the characters from $ i $ to $ j $ in non-decreasing order if $ k=1 $ or in non-increasing order if $ k=0 $ .\n\nOutput the final string after applying the queries.",
    "inputFormat": "The first line will contain two integers $ n,q $ ( $ 1<=n<=10^{5} $ , $ 0<=q<=50000 $ ), the length of the string and the number of queries respectively.\n\nNext line contains a string $ S $ itself. It contains only lowercase English letters.\n\nNext $ q $ lines will contain three integers each $ i,j,k $ ( $ 1<=i<=j<=n $ , ![](https://cdn.luogu.com.cn/upload/vjudge_pic/CF558E/7c3e064c95015e1bd5569e78df83991726b5fb24.png)).",
    "outputFormat": "Output one line, the string $ S $ after applying the queries.",
    "samples": [
        [
            "10 5\nabacdabcda\n7 10 0\n5 8 1\n1 4 0\n3 6 0\n7 10 1\n",
            "cbcaaaabdd"
        ],
        [
            "10 1\nagjucbvdfk\n1 10 1\n",
            "abcdfgjkuv"
        ]
    ],
    "hint": "First sample test explanation:\n\n![](https://cdn.luogu.com.cn/upload/vjudge_pic/CF558E/39812d297b72578842edac4711612bcaf8f08f55.png)\n\n![](https://cdn.luogu.com.cn/upload/vjudge_pic/CF558E/6cf00260e704a305c81e1f57b87405efa2610fa7.png)\n\n![](https://cdn.luogu.com.cn/upload/vjudge_pic/CF558E/8d72452272093b12cc5f5081cf07220bba9298d5.png)\n\n![](https://cdn.luogu.com.cn/upload/vjudge_pic/CF558E/51ddb7e0620c1f3452d956f281c3537d11d07fb3.png)\n\n![](https://cdn.luogu.com.cn/upload/vjudge_pic/CF558E/47cfdfe8b8cb10e651ce3dbdd53d8f068aca3e79.png)",
    "translation": "\u9898\u76ee\u5927\u610f\uff1a \u7ed9\u5b9a\u4e00\u4e2a\u957f\u5ea6\u4e0d\u8d85\u8fc710^5\u7684\u5b57\u7b26\u4e32\uff08\u5c0f\u5199\u82f1\u6587\u5b57\u6bcd\uff09\uff0c\u548c\u4e0d\u8d85\u8fc750000\u4e2a\u64cd\u4f5c\u3002\n\n\u6bcf\u4e2a\u64cd\u4f5c L R K \u8868\u793a\u7ed9\u533a\u95f4[L,R]\u7684\u5b57\u7b26\u4e32\u6392\u5e8f\uff0cK=1\u4e3a\u5347\u5e8f\uff0cK=0\u4e3a\u964d\u5e8f\u3002\n\n\u6700\u540e\u8f93\u51fa\u6700\u7ec8\u7684\u5b57\u7b26\u4e32\u3002\n"
}