{
    "description": "A function ![](https://cdn.luogu.com.cn/upload/vjudge_pic/CF601B/430ebcefe96c88310ccd261882b0ff945145df52.png) is called Lipschitz continuous if there is a real constant $ K $ such that the inequality $ |f(x)-f(y)|<=K\u00b7|x-y| $ holds for all ![](https://cdn.luogu.com.cn/upload/vjudge_pic/CF601B/261d3c24b04ab9fe2bfe5b80cef7a0d93e455362.png). We'll deal with a more... discrete version of this term.\n\nFor an array ![](https://cdn.luogu.com.cn/upload/vjudge_pic/CF601B/ccfdce10ff74cd472d9792ed111da871e7a50f00.png), we define it's Lipschitz constant ![](https://cdn.luogu.com.cn/upload/vjudge_pic/CF601B/dea73c73292e257d3ec0493d833cd87ce60d4100.png) as follows:\n\n- if $ n&lt;2 $ , ![](https://cdn.luogu.com.cn/upload/vjudge_pic/CF601B/3ff8c17ca1f7b3e483996c6b0a65fe8821444f77.png)\n- if $ n>=2 $ , ![](https://cdn.luogu.com.cn/upload/vjudge_pic/CF601B/02820989bea357555f19945647d60c22d98153a5.png) over all $ 1<=i&lt;j<=n $\n\nIn other words, ![](https://cdn.luogu.com.cn/upload/vjudge_pic/CF601B/7f78e6e27f8b58a065808f48924984c382457583.png) is the smallest non-negative integer such that $ |h[i]-h[j]|<=L\u00b7|i-j| $ holds for all $ 1<=i,j<=n $ .\n\nYou are given an array ![](https://cdn.luogu.com.cn/upload/vjudge_pic/CF601B/3c996d04a1a028eb850ea279befed0060d54e243.png) of size $ n $ and $ q $ queries of the form $ [l,r] $ . For each query, consider the subarray ![](https://cdn.luogu.com.cn/upload/vjudge_pic/CF601B/fab57d281524c7eb59473c192b040dba9062a2ef.png); determine the sum of Lipschitz constants of all subarrays of ![](https://cdn.luogu.com.cn/upload/vjudge_pic/CF601B/933dbfa1108f94092075e7b3a5cee6b27ee2f330.png).",
    "inputFormat": "The first line of the input contains two space-separated integers $ n $ and $ q $ ( $ 2<=n<=100000 $ and $ 1<=q<=100 $ ) \u2014 the number of elements in array ![](https://cdn.luogu.com.cn/upload/vjudge_pic/CF601B/3c996d04a1a028eb850ea279befed0060d54e243.png) and the number of queries respectively.\n\nThe second line contains $ n $ space-separated integers ![](https://cdn.luogu.com.cn/upload/vjudge_pic/CF601B/a894c656178c8b0dc4902212cccb3f110230b59c.png) (![](https://cdn.luogu.com.cn/upload/vjudge_pic/CF601B/9e8c0fade12c84c7014a7013ed96f5825cfef4b1.png)).\n\nThe following $ q $ lines describe queries. The $ i $ -th of those lines contains two space-separated integers $ l_{i} $ and $ r_{i} $ ( $ 1<=l_{i}&lt;r_{i}<=n $ ).",
    "outputFormat": "Print the answers to all queries in the order in which they are given in the input. For the $ i $ -th query, print one line containing a single integer \u2014 the sum of Lipschitz constants of all subarrays of ![](https://cdn.luogu.com.cn/upload/vjudge_pic/CF601B/5d9ebef2ff7149a76a7b22b08cb78cb7d7617492.png).",
    "samples": [
        [
            "10 4\n1 5 2 9 1 3 4 2 1 7\n2 4\n3 8\n7 10\n1 9\n",
            "17\n82\n23\n210\n"
        ],
        [
            "7 6\n5 7 7 4 6 6 2\n1 2\n2 3\n2 6\n1 7\n4 7\n3 5\n",
            "2\n0\n22\n59\n16\n8\n"
        ]
    ],
    "hint": "In the first query of the first sample, the Lipschitz constants of subarrays of ![](https://cdn.luogu.com.cn/upload/vjudge_pic/CF601B/6f9417fdcb9c3ca8d78dd9307c5187f8fb187e89.png) with length at least $ 2 $ are:\n\n- ![](https://cdn.luogu.com.cn/upload/vjudge_pic/CF601B/ad0807635c6133e89feb982a2e00b9c60b15e05e.png)\n- ![](https://cdn.luogu.com.cn/upload/vjudge_pic/CF601B/b5fd24d5adf442c68d175bf047b1975f7d5e9c25.png)\n- ![](https://cdn.luogu.com.cn/upload/vjudge_pic/CF601B/bb2421b16fa9a9eeeb4115e7a2a3b1e115becb80.png)\n\nThe answer to the query is their sum.",
    "translation": "**\u3010\u9898\u76ee\u7ffb\u8bd1\u3011**\n\n\u5bf9\u4e8e\u4e00\u4e2a\u5e8f\u5217 $v_{1...n}$\uff0c\u5f53 $1\\leq x<y\\leq n$ \u4e14 $x,y$ \u5747\u4e3a\u6574\u6570\u65f6\uff0c\u540c\u6837\u6ee1\u8db3$|v_x-v_y|\\leq K\\times |x-y|$\uff0c\u5219\u79f0 $K$ \u7684\u6700\u5c0f\u6574\u6570\u503c\u4e3a\u5e8f\u5217 $v$ \u7684 Lipschitz \u5e38\u6570\u3002\u73b0\u5728\u7ed9\u4f60\u4e00\u4e2a\u957f\u5ea6\u4e3a $n$ \u7684\u5e8f\u5217 $v$ \u5e76\u7ed9\u51fa $q$ \u4e2a\u8be2\u95ee\uff0c\u5bf9\u4e8e\u6bcf\u5bf9\u8be2\u95ee $[l,r]$\uff0c \u4f60\u9700\u8981\u6c42\u51fa $v_{l...r}$ \u7684\u6240\u6709\u8fde\u7eed\u5b50\u5e8f\u5217\uff08\u5b50\u6bb5\uff09$v_{x,y}(l\\leq x<y\\leq r)$ \u7684 Lipschitz \u5e38\u6570\u4e4b\u548c\u3002\n\n**\u3010\u8f93\u5165\u683c\u5f0f\u3011**\n\n\u7b2c\u4e00\u884c\u4e24\u4e2a\u6574\u6570 $n$ \u548c $q$\uff0c\u5206\u522b\u8868\u793a\u5e8f\u5217\u7684\u957f\u5ea6\u4ee5\u53ca\u8be2\u95ee\u7684\u4e2a\u6570\u3002 \n\n\u7b2c\u4e8c\u884c $n$ \u4e2a\u6570\uff0c\u8868\u793a\u5e8f\u5217 $v,(0\\leq v_i\\leq 10^8)$\u3002\u63a5\u4e0b\u6765 $q$ \u884c\uff0c\u6bcf\u884c\u4e24\u4e2a\u6570 $l$ \u548c $r$\uff0c\u8868\u793a\u8be2\u95ee\u7684\u533a\u95f4\u4e3a $[l,r]$\u3002\n\n**\u3010\u8f93\u51fa\u683c\u5f0f\u3011**\n\n\u5bf9\u4e8e\u6bcf\u4e2a\u8be2\u95ee\uff0c\u8f93\u51fa\u4e00\u884c\u4e00\u4e2a\u6570\uff0c\u5373 $v_{l,r}$ \u7684\u6240\u6709\u8fde\u7eed\u5b50\u5e8f\u5217\uff08\u5b50\u6bb5\uff09\u7684 Lipschitz \u5e38\u6570\u4e4b\u548c\u3002"
}