[
    {
        "content": "[\u53cc\u500d\u7ecf\u9a8c](https://www.luogu.com.cn/problem/SP283)\n\n------------\n\u5148\u6765\u8003\u8651\u4e00\u4e2a\u201c\u7b80\u5316\u7248\u201d\uff1a\u5047\u8bbe\u7b2cN\u4e2a\u5c0f\u65f6\u4e0e\u6b21\u65e5\u7b2c\u4e00\u4e2a\u5c0f\u65f6\u4e0d\u662f\u76f8\u8fde\u7684\uff0c\u90a3\u4e48\u8fd9\u5c31\u662f\u4e00\u4e2a\u660e\u663e\u7684DP\u9898\uff1a\n\n\u7528$dp_{i,j,0/1}$\u6765\u8868\u793a\u5728\u7b2ci\u4e2a\u5c0f\u65f6\uff0c\u5df2\u7ecf\u4f11\u606f\u4e86j\u4e2a\u5c0f\u65f6\uff0c0\u8868\u793a\u8fd9\u4e2a\u5c0f\u65f6\u6ca1\u5728\u4f11\u606f\uff0c1\u8868\u793a\u8fd9\u4e2a\u5c0f\u65f6\u6b63\u5728\u4f11\u606f\u3002\n\n\u72b6\u6001\u8f6c\u79fb\u65b9\u7a0b\u5c31\u662f\uff1a\n```cpp\ndp[i][j][0]=max(dp[i-1][j][0],dp[i-1][j][1]);\ndp[i][j][1]=max(dp[i-1][j-1][0],dp[i-1][j-1][1]+u[i]);\n```\n\u521d\u503c\uff1a$dp_{1,1,1}=0$\uff0c$dp_{1,0,0}=0$\uff0c\u5176\u4f59\u4e3a-INF\u3002\n\n\u7b54\u6848\uff1a$\\max(dp_{n,b,0},dp_{n,b,1})$\u3002\n\n------------\n\u4f46\u95ee\u9898\u662f\u7b2cN\u4e2a\u5c0f\u65f6\u4e0e\u6b21\u65e5\u7b2c\u4e00\u4e2a\u5c0f\u65f6\u662f\u76f8\u8fde\u7684\uff0c\u4e0a\u9762\u7684\u65b9\u6cd5\u4e0d\u80fd\u76f4\u63a5\u7528\u3002\u65e2\u7136\u8fd9\u6837\uff0c\u90a3\u5c31\u518d\u6765\u4e00\u6b21\u5f3a\u5236\u8fde\u63a5\uff1a\n\n\u5f3a\u5236\u8ba9\u7b2cN\u4e2a\u5c0f\u65f6\u7761\u89c9\uff0c\u8ba9\u6b21\u65e5\u7b2c\u4e00\u4e2a\u5c0f\u65f6\u719f\u7761\u3002\n\n\u72b6\u6001\u8f6c\u79fb\u65b9\u7a0b\u5982\u4e0a\u3002\n\n\u521d\u503c\uff1a$dp_{1,1,1}=u_{1}$\uff0c$dp_{1,0,0}=0$\uff0c\u5176\u4f59\u4e3a-INF\u3002\n\n\u7b54\u6848\uff1a$dp_{n,b,1}$\n\n------------\n\u5177\u4f53\u6765\u8bf4\uff0c\u6211\u4eec\u53ef\u4ee5\u5148\u5c06\u7b2cN\u4e2a\u5c0f\u65f6\u4e0e\u6b21\u65e5\u7b2c\u4e00\u4e2a\u5c0f\u65f6\u65ad\u5f00\uff0c\u7136\u540e\u7528\u4e0a\u9762\u7684\u201c\u7b80\u5316\u7248\u201d\u7684\u65b9\u6cd5\u6765\u5f97\u5230\u4e00\u4e2a\u7b54\u6848\u3002\u518d\u5f3a\u5236\u8ba9\u7b2cN\u4e2a\u5c0f\u65f6\u7761\u89c9\uff0c\u8ba9\u6b21\u65e5\u7b2c\u4e00\u4e2a\u5c0f\u65f6\u719f\u7761\uff0c\u7528\u4e0a\u9762\u8ba8\u8bba\u7684\u5f3a\u5236\u8fde\u63a5\u7684\u65b9\u6cd5\u5f97\u5230\u7b2c\u4e8c\u4e2a\u7b54\u6848\uff0c\u4e24\u8005\u53d6\u6700\u5927\u503c\u5373\u53ef\u3002\n\n------------\n$AC\\ Code:$\n```cpp\n#include<bits/stdc++.h>\nusing namespace std;\nint dp[3831][3831][2],n,b,u[3831],ans;\nint main() {\n\tscanf(\"%d%d\",&n,&b);\n\tfor(int i=1;i<=n;i++)scanf(\"%d\",u+i);\n\tmemset(dp,-0x3f,sizeof(dp));\n\tdp[1][1][1]=dp[1][0][0]=0;\n\tfor(int i=2;i<=n;i++){\n\t\tdp[i][0][0]=dp[i-1][0][0];\n\t\tfor(int j=1;j<=b;j++){\n\t\t\tdp[i][j][0]=max(dp[i-1][j][0],dp[i-1][j][1]);\n\t\t\tdp[i][j][1]=max(dp[i-1][j-1][0],dp[i-1][j-1][1]+u[i]);\n\t\t}\n\t}\n\tans=max(dp[n][b][0],dp[n][b][1]);\n\tmemset(dp,-0x3f,sizeof(dp));\n\tdp[1][1][1]=u[1];\n\tdp[1][0][0]=0;\n\tfor(int i=2;i<=n;i++){\n\t\tdp[i][0][0]=dp[i-1][0][0];\n\t\tfor(int j=1;j<=b;j++){\n\t\t\tdp[i][j][0]=max(dp[i-1][j][0],dp[i-1][j][1]);\n\t\t\tdp[i][j][1]=max(dp[i-1][j-1][0],dp[i-1][j-1][1]+u[i]);\n\t\t}\n\t}\n\tans=max(ans,dp[n][b][1]);\n\tprintf(\"%d\\n\",ans);\n\treturn 0;\n}\n```\n\u8fd9\u662f\u4e00\u4e2a\u6bd4\u8f83\u5e38\u89c1\u7684\u89e3\u51b3\u73af\u5f62DP\u7684\u7b56\u7565\uff0c\u4e00\u5b9a\u8981\u8bb0\u4f4f",
        "postTime": 1585380864,
        "uid": 261370,
        "name": "Andy_Lin",
        "ccfLevel": 0,
        "title": "\u9898\u89e3 P6064 \u3010[USACO05JAN]Naptime G\u3011"
    },
    {
        "content": "## \u9898\u76ee\u5927\u610f\n\n\n------------\n\u7ed9\u4e00\u4e2a\u73af\uff0c\u6709 $N$ \u4e2a\u6709\u6743\u503c\u7684\u8282\u70b9\u3002\u9009\u53d6\u5176\u4e2d\u7684 $B$ \u4e2a\uff0c\u4f7f\u5176\u6743\u503c\u548c\u6700\u5927\uff0c\u4f46\u662f\u5bf9\u4e8e\u6bcf\u4e00\u6bb5\u8282\u70b9\u8fde\u7eed\u7684\u533a\u95f4\uff0c\u7b2c\u4e00\u4e2a\u70b9\u7684\u6743\u503c\u4e0d\u8ba1\u5165\u7b54\u6848\uff08\u201c\u7b2c\u4e00\u4e2a\u201d\u5f53\u7136\u662f\u4ece\u540c\u4e00\u4e2a\u65b9\u5411\u800c\u8a00\uff09\u3002\n\n\n------------\n## \u89e3\u51b3\u65b9\u6848\n\u5f88\u660e\u663e\u662f\u73af\u5f62 DP \u554a\u3002\u8981\u601d\u8003\u8fd9\u9053\u9898\uff0c\u4e0d\u59a8\u5047\u8bbe\u7b2c $N$ \u4e2a\u70b9\u548c\u7b2c $1$ \u4e2a\u70b9\u662f\u65ad\u5f00\u7684\u3002\n\n\u6211\u4eec**\u8bbe $f_{i,j,1}$ \u6307\u524d $i$ \u4e2a\u70b9\u4e2d\u53d6\u4e86 $j$ \u4e2a\uff0c\u4e14\u5f53\u524d\u70b9\u9009\u62e9\u4e86\u3002\u8bbe $f_{i,j,0}$ \u6307\u524d $i$ \u4e2a\u70b9\u4e2d\u53d6\u4e86 $j$ \u4e2a\uff0c\u4e14\u5f53\u524d\u70b9\u6ca1\u6709\u9009\u62e9**\u3002\u5982\u679c\u524d $i$ \u4e2a\u70b9\u4e2d\u53d6\u4e86 $j$ \u4e2a\uff0c\u4e14\u524d\u4e00\u4e2a\u70b9\u9009\u4e0a\u4e86\uff0c\u90a3\u4e48 $f_{i,j,1}$ \u5c31\u5e94\u8be5\u662f\u4ece\u4ee5\u4e0b\u4e24\u79cd\u65b9\u6848\u53d6\u6700\u5927\u503c\uff1a\u524d\u4e00\u4e2a\u6570\u6ca1\u9009\uff0c\u5f53\u524d\u6570\u662f\u63a5\u4e0b\u6765\u4e00\u4e32\u5143\u7d20\u7684\u9996\u4e2a\uff1b\u524d\u4e00\u4e2a\u6570\u9009\u4e86\uff0c\u6211\u4eec\u628a\u5f53\u524d\u6570\u52a0\u5230\u524d\u4e00\u4e2a\u6570\u9009\u4e86\u7684\u7b54\u6848\u4e2d\uff08\u65b9\u7a0b\u4e2d\u6ce8\u610f $j$ \u8981\u51cf $1$\uff01\u56e0\u4e3a\u524d $i$ \u4e2a\u6570\u4e2d\u9009\u7684 $j$ \u4e2a\u6570\u5305\u542b\u4e86\u5f53\u524d\u6570\u5b57\uff09\u3002\u5982\u679c\u5f53\u524d\u6570\u4e0d\u9009\uff0c\u4e5f\u5dee\u4e0d\u591a\uff0c\u770b\u770b\u65b9\u7a0b\u4e5f\u597d\u7406\u89e3\u3002\u8f6c\u79fb\u65b9\u7a0b\u5982\u4e0b\uff1a\n```\nf[i][j][1]=max(f[i-1][j-1][0],f[i-1][j-1][1]+w[i]);\nf[i][j][0]=max(f[i-1][j][0],f[i-1][j][1]);\n\n```\n\u522b\u5fd8\u4e86\u521d\u59cb\u5316\uff01\n\n```\nf[1][0][0]=0;\nf[1][1][1]=0;\n//\u5176\u4f59\u4e3a\u8d1f\u65e0\u7a77\n```\n\n\u7136\u800c\u6b8b\u9177\u7684\u662f\uff0c\u524d\u9762\u7684\u4e00\u5207\u90fd\u5efa\u7acb\u5728\u4e00\u4e2a\u7f8e\u597d\u7684\u8bbe\u60f3\u4e0a\uff1a\u7b2c $N$ \u4e2a\u70b9\u548c\u7b2c $1$ \u4e2a\u70b9\u662f\u65ad\u5f00\u7684\u3002\u90a3\u4e48\u6211\u4eec\u5e94\u8be5\u5982\u4f55\u5904\u7406\u8fd9\u4e00\u70b9\u5462\uff1f\n\n\n------------\n\n#### \u65b9\u6cd5\u4e00\n\n\u53d7[\u77f3\u5b50\u5408\u5e76](https://www.luogu.com.cn/problem/P1880)\u542f\u53d1\uff0c\u8bbe\u7b2c $N$ \u4e2a\u70b9\u548c\u7b2c $1$ \u4e2a\u70b9\u662f\u65ad\u5f00\u7684\uff0c\u6211\u4eec\u8003\u8651\u628a\u8fd9\u4e2a\u533a\u95f4\u590d\u5236\u4e00\u4efd\u653e\u5230\u539f\u6765\u7684\u8fd9\u4e2a\u533a\u95f4\u540e\u9762\uff0c\u7136\u540e DP\u3002\u6700\u540e\u4ece\u8fd9\u4e2a\u957f\u5ea6\u4e3a $2 * N$ \u7684\u533a\u95f4\u91cc\u6240\u6709\u957f\u5ea6\u4e3a $N$ \u7684\u60c5\u51b5\u4e2d\u53d6\u6700\u4f18\u89e3\u3002\u4f46\u6211\u6ca1\u8fd9\u4e48\u641e\uff0c\u800c\u4e14\u7a7a\u95f4\u4f3c\u4e4e\u6709\u95ee\u9898\u3002\u4e0d\u77e5\u9053\u884c\u4e0d\u884c\u5f97\u901a\uff0c\u53cd\u6b63\u6211\u4eec\u6709\u66f4\u597d\u7684\u65b9\u6cd5\uff01\uff01\uff01\n\n#### \u65b9\u6cd5\u4e8c\n\n\u6211\u4eec\u5206\u7c7b\u8ba8\u8bbaDP \u4e24\u6b21\uff01\n\n##### \u60c5\u51b5\u4e00\n\n\u7b2c $N$ \u4e2a\u6570\u4e0d\u9009\u3002\u8fd9\u6837\u5373\u4f7f\u9009\u4e86\u7b2c $1$ \u4e2a\u6570\uff0c\u5b83\u7684\u503c\u4e5f\u6ca1\u4ec0\u4e48\u7528\uff0c\u6240\u4ee5\u5b8c\u5168\u53ef\u4ee5\u5047\u8bbe\u7b2c $N$ \u4e2a\u70b9\u548c\u7b2c $1$ \u4e2a\u70b9\u662f\u65ad\u5f00\u7684\u4e86\u3002\n\n##### \u60c5\u51b5\u4e8c\n\n\u7b2c $N$ \u4e2a\u6570\u9009\u3002\u8fd9\u6837\u5c31\u4e0d\u53ef\u4ee5\u5047\u8bbe\u7b2c $N$ \u4e2a\u70b9\u548c\u7b2c $1$ \u4e2a\u70b9\u662f\u65ad\u5f00\u7684\u4e86\u3002\u4f46\u8fd9\u6837\u6211\u4eec\u53ef\u4ee5\u5f3a\u5236\u9009\u53d6\u7b2c $N$ \u4e2a\u6570\u3002\u7b2c $N$ \u4e2a\u6570\u9009\u4e86\uff0c\u90a3\u4e48\u7b2c $1$ \u4e2a\u6570\u7684\u6743\u503c\u5c31\u53ef\u4ee5\u53d1\u6325\u4f5c\u7528\u4e86\u3002\u8f6c\u79fb\u65b9\u7a0b\u4e0d\u53d8\uff0c\u53ea\u8981\u6539\u52a8\u4e00\u4e0b\u521d\u59cb\u5316\u5373\u53ef\uff1a\n```\nf[1][0][0]=0;\nf[1][1][1]=w[1];\n//\u5176\u4f59\u4e3a\u8d1f\u65e0\u7a77\n```\n\n\n------------\n## \u4e0a\u4ee3\u7801\n```\n#include<bits/stdc++.h>\nusing namespace std;\nint w[3840];\nint f[3840][3840][2];\nint INF=0x3f3f3f3f;\nint main(){\n\tint n,m;\n\tcin>>n>>m;\n\tfor(int i=1;i<=n;i++)\n\t\tcin>>w[i];\n\tmemset(f,-0x3f,sizeof f);\n\tf[1][0][0]=0;\n\tf[1][1][1]=0;\n\tfor(int i=2;i<=n;i++){\n\t\tfor(int j=0;j<=m;j++){\n\t\t\tf[i][j][0]=max(f[i-1][j][0],f[i-1][j][1]);\n\t\t\tf[i][j][1]=-INF;\n\t\t\tif(j)\n\t\t\t\tf[i][j][1]=max(f[i-1][j-1][0],f[i-1][j-1][1]+w[i]);\n\t\t}\n\t}\n\tint ans=f[n][m][0];\n\tmemset(f,-0x3f3f3f,sizeof f);\n\tf[1][0][0]=0;\n\tf[1][1][1]=w[1];\n\tfor(int i=2;i<=n;i++){\n\t\tfor(int j=0;j<=m;j++){\n\t\t\tf[i][j][0]=max(f[i-1][j][0],f[i-1][j][1]);\n\t\t\tf[i][j][1]=-INF;\n\t\t\tif(j)\n\t\t\t\tf[i][j][1]=max(f[i-1][j-1][0],f[i-1][j-1][1]+w[i]);\n\t\t}\n\t}\n\tans=max(f[n][m][1],ans);\n\tcout<<ans<<endl;\n}\n```\n\u4e0b\u9762\u8fd9\u4e2a\u52a0\u4e86\u6eda\u52a8\u6570\u7ec4\uff0c\u5438\u53e3\u6c27\u5c31\u662f\u76ee\u524d\u6700\u4f18\u89e3\u54e6\uff01\uff08~~\u5176\u5b9e\u662f\u5927\u4f6c\u4eec\u61d2\u5f97\u5438\u6c27~~\uff09\n\n```\n#include<bits/stdc++.h>\nusing namespace std;\nint w[3840];\nint f[2][3840][2];\nint INF=0x3f3f3f3f;\nint main(){\n\tint n,m;\n\tcin>>n>>m;\n\tfor(int i=1;i<=n;i++)\n\t\tcin>>w[i];\n\tmemset(f,-0x3f3f3f,sizeof f);\n\tf[1][0][0]=0;\n\tf[1][1][1]=0;\n\tfor(register int i=2;i<=n;i++){\n\t\tfor(register int j=0;j<=m;j++){\n\t\t\tf[i&1][j][0]=max(f[(i+1)&1][j][0],f[(i+1)&1][j][1]);\n\t\t\tf[i&1][j][1]=-INF;\n\t\t\tif(j)\n\t\t\t\tf[i&1][j][1]=max(f[(i+1)&1][j-1][0],f[(i+1)&1][j-1][1]+w[i]);\n\t\t}\n\t}\n\tint ans=f[n&1][m][0];\n\tmemset(f,-0x3f3f3f,sizeof f);\n\tf[1][0][0]=0;\n\tf[1][1][1]=w[1];\n\tfor(register int i=2;i<=n;i++){\n\t\tfor(register int j=0;j<=m;j++){\n\t\t\tf[i&1][j][0]=max(f[(i+1)&1][j][0],f[(i+1)&1][j][1]);\n\t\t\tf[i&1][j][1]=-INF;\n\t\t\tif(j)\n\t\t\t\tf[i&1][j][1]=max(f[(i+1)&1][j-1][0],f[(i+1)&1][j-1][1]+w[i]);\n\t\t}\n\t}\n\tans=max(f[n&1][m][1],ans);\n\tcout<<ans<<endl;\n}\n```",
        "postTime": 1626177977,
        "uid": 140360,
        "name": "LKawaii",
        "ccfLevel": 0,
        "title": "P6064\u9898\u89e3"
    },
    {
        "content": "## Update on 2020.12.1\n\u9996\u5148\uff0c\u611f\u8c22\u4e00\u4e0b\u5927\u4f6c\u4eec\u5bf9\u6211\u7684\u542f\u53d1\u3002~~\uff08\u4e0d\u7136\u6211\u53ef\u80fd\u4e00\u8f88\u5b50\u90fd\u6ca1\u6cd5AC\uff09~~\n\n\u4e0b\u9762\u5f00\u59cb\u6b63\u9898\u3002\n\n\n------------\n# Step 1\uff1a\u5206\u6790\u52a8\u5f52\u65b9\u7a0b\n\u5148\u5047\u8bbe\u6ca1\u6709\u4e00\u5929\u4e00\u5929\u5faa\u73af\u3002\n\n\u8bbe$f(i,j,0/1)$\u8868\u793a\u4ece\u7b2ci\u4e2a\u5c0f\u65f6\u5f00\u59cb\uff0c\u5df2\u7ecf\u7761\u4e86j\u4e2a\u5c0f\u65f6\uff0c\u5f53\u524d\u6709\u6ca1\u6709\u5728\u7761\u89c9\uff080\u8868\u793a\u4e0d\u5728\u7761\u89c9\uff0c1\u8868\u793a\u5728\u7761\u89c9\uff09\u3002\n\n\n\u52a8\u5f52\u65b9\u7a0b\uff1a\n\n\uff08\u521d\u59cb\u5316\u4e3a$f(1,1,1)=f(1,1,0)=f(1,0,0)$,\u5176\u4ed6\u4e3a-0x3f\uff09\n\t\n    \n```cpp\nf[i][j][0]=max(f[i-1][j][0],f[i-1][j][1]);\n\nf[i][j][1]=max(f[i-1][j-1][1]+a[i],f[i-1][j-1][0]);\n```\n\n\n\n  \n\u7ed3\u679c\uff1a$max(f(n,b,0),f(n,b,1))$\n\n\n\n------------\n# Step 2\uff1a\u6539\u8fdb\u52a8\u5f52\u65b9\u7a0b\n\u8fd9\u9898\u4e00\u770b\u5c31\u80fd\u770b\u51fa\u6765\u662f\u73af\u5f62\u533a\u95f4dp\uff0c\u800c\u89e3\u51b3\u8fd9\u79cd\u95ee\u9898\u6700\u5e38\u89c1\u7684\u65b9\u6cd5\u6709\u4e24\u79cd\u3002\n\n- **\u500d\u957f\u533a\u95f4**\n- **\u5f3a\u5236\u8fde\u63a5**\n\n\u4e2a\u4eba\u6bd4\u8f83\u63a8\u8350\u7b2c\u4e00\u79cd\n~~\uff08\u6211\u7edd\u5bf9\u4e0d\u4f1a\u544a\u8bc9\u4f60\u56e0\u4e3a\u6211\u4e0d\u4f1a\u7b2c\u4e8c\u79cd\uff09~~\u3002\n\n\u4f46\u662f\u8fd9\u9898\u500d\u957f\u627e\u4e0d\u51fa\u5173\u7cfb\uff0c\u6240\u4ee5\u53ea\u597d\u5f3a\u5236\u8fde\u4e00\u4e0b\u4e86\u3002\n\n\u6b65\u9aa4\u4e3a\uff1a\u5148\u6309step 1\u4e2d\u7684dp\u4e00\u904d\uff0c\u518d\u5f3a\u5236\u8ba9\u7b2c\u4e00\u4e2a\u5c0f\u65f6\u719f\u7761dp\u4e00\u904d\u3002\u4e5f\u5c31\u662f\u8bf4\u7b2c\u4e8c\u904d\u521d\u59cb\u5316\u65f6\u8ba9$f(1,1,1)$=$a[1]$ \u5c31\u53ef\u4ee5\u4e86\u3002\n\n\u7ed3\u679c\uff1a\t$f(n,b,1)$ (\u7531\u4e8e\u7b2c\u4e00\u4e2a\u5c0f\u65f6\u5fc5\u987b\u719f\u7761\uff09\n\n\n\n------------\n\u4ee5\u4e0a\u4e24\u4e2a\u7ed3\u679c\u53d6\u6700\u5927\u503c\u5c31\u53ef\u4ee5\u4e86\u3002\n\n\n------------\n# Step 3\uff1aCode\n\u4e0b\u9762\u9644\u4e0a\u4ee3\u7801\uff1a\n```cpp\n#include <iostream>\n#include <cstring>\nusing namespace std;\n\nint n,b,a[3831],ans;\nint f[3831][3831][2];//f[i][j][0\u30011]\u8868\u793a\u4ece\u7b2ci\u6bb5\u5f00\u59cb\u7761j\u6bb5\u5f53\u524d\uff08\u6ca1\u7761\u3001\u7761\uff09\u7684\u6700\u5927u\n\nint max(int a,int b)//\u81ea\u5df1\u5199\u7684max\uff0c\u66f4\u5feb\n{\n\treturn a>b?a:b;\n}\n\nvoid read()//\u8bfb\u5165\n{\n\tint i;\n\tfor(i=1;i<=n;i++)\n\t{\n\t\tcin>>a[i];\n\t}\n}\n\nvoid dp()//\u52a8\u5f52\u51fd\u6570\n{\n\tint i,j;\n\tfor(i=2;i<=n;i++)\n\t{\n\t\tf[i][0][0]=f[i-1][0][0];\n\t\tfor(j=1;j<=b;j++)\n\t\t{\n\t\t\tf[i][j][0]=max(f[i-1][j][0],f[i-1][j][1]);\n\t\t\tf[i][j][1]=max(f[i-1][j-1][1]+a[i],f[i-1][j-1][0]);\n\t\t}\n\t}\n}\n\nint main()\n{\n\tint i;\n\tmemset(f,-0x3f,sizeof(f));//\u521d\u59cb\u5316\u4e3a-inf\n\tcin>>n>>b;\n\tread();\n\tf[1][1][1]=0;\n\tf[1][1][0]=0;\n\tf[1][0][0]=0;\n\tdp();\n\tans=max(f[n][b][0],f[n][b][1]);\n\tmemset(f,-0x3f,sizeof(f));\n\tf[1][1][1]=a[1];\n\tf[1][0][0]=0;\n\tf[1][1][0]=0;\n\tdp();\n\tans=max(ans,f[n][b][1]);//\u53d6\u6700\u5927\n\tcout<<ans<<endl;//\u8f93\u51fa\n\treturn 0;\n}\n\n\t\n\n```\n\n\n\n\n\n# \u7b2c\u4e00\u7bc7\u9898\u89e3\uff0c\u6c42\u901a\u8fc7\uff01\n\n\n",
        "postTime": 1604718719,
        "uid": 304775,
        "name": "linyinuo2008",
        "ccfLevel": 0,
        "title": "\u9898\u89e3 P6064 \u3010[USACO05JAN]Naptime G\u3011"
    },
    {
        "content": "\u5c0f\u6e05\u65b0 dp \u9898\u3002\n\n\u8bbe $f_{i,j,0/1}$ \u4e3a\u524d $i$ \u6bb5\u7761\u4e86 $j$ \u6bb5\u4e14\u76ee\u524d\u8fd9\u6bb5\u7761\u6ca1\u7761\uff0c$1$ \u8868\u793a\u7761\u4e86\u3002\n\n\u8f6c\u79fb\u65b9\u7a0b\uff1a\n\n$$f_{i,j,0}=\\max(f_{i-1,j,0},f_{i-1,j,1})$$\n\n$$f_{i,j,1}=\\max(f_{i-1,j-1,0},f_{i-1,j-1,1}+a_i)$$\n\n$\\max(f_{n,b,0},f_{n,b,1})$ \u5c31\u662f\u7b54\u6848\u3002\n\n\u4f46\u662f\uff0c\u8fd9\u6837\u4e0d\u80fd\u5904\u7406\u73af\u3002\u53ef\u4ee5\u901a\u8fc7\u5f3a\u5236\u9009\u7b2c\u4e00\u4e2a\u548c\u5f3a\u5236\u4e0d\u9009\u7b2c\u4e00\u4e2a\u8fd9\u4e24\u4e2a\u60c5\u51b5\u5206\u522b\u505a\u4e00\u6b21 dp \u6765\u89e3\u51b3\u3002\n\n\u5f3a\u5236\u4e0d\u9009\u7684\u521d\u59cb\u5316\u662f $f_{1,1,1}=0$\uff0c\u5f3a\u5236\u9009\u7684\u521d\u59cb\u5316\u5c31\u662f $f_{1,1,1}=a_1$\u3002\n\n\u6838\u5fc3\u4ee3\u7801\uff1a\n\n```cpp\nvoid solve()\n{\n\tmemset(f,128,sizeof f);\n\tcin>>n>>b;\n\tfor(int i=1;i<=n;i++)\n\tcin>>a[i];\n\tf[1][1][1]=0;\n\tfor(int i=1;i<=n;i++) f[i][0][0]=0;\n\tfor(int i=2;i<=n;i++)\n\tfor(int j=1;j<=b;j++)\n\t{\n\t\tf[i][j][0]=max(f[i-1][j][0],f[i-1][j][1]);\n\t\tf[i][j][1]=max(f[i-1][j-1][0],f[i-1][j-1][1]+a[i]);\n\t } \n\t int ans=max(f[n][b][0],f[n][b][1]);\n\t memset(f,128,sizeof f);\n\t f[1][1][1]=a[1];\n\t for(int i=1;i<=n;i++) f[i][0][0]=0;\n\t for(int i=2;i<=n;i++)\n\t for(int j=1;j<=b;j++)\n\t {\n\t\tf[i][j][0]=max(f[i-1][j][0],f[i-1][j][1]);\n\t\tf[i][j][1]=max(f[i-1][j-1][0],f[i-1][j-1][1]+a[i]);\n\t }\n\t cout<<max(ans,f[n][b][1])<<endl;\n} \n```\n",
        "postTime": 1598321536,
        "uid": 196899,
        "name": "lndjy",
        "ccfLevel": 9,
        "title": "\u9898\u89e3 P6064 \u3010[USACO05JAN]Naptime G\u3011"
    },
    {
        "content": "\u53c2\u8003\u8d44\u6599~~\u6284\u81ea~~\uff1a\u300a\u7b97\u6cd5\u7ade\u8d5b\uff1a\u8fdb\u9636\u6307\u5357\u300b\n## \u7b97\u6cd5\u5206\u6790\n\u8fd9\u662f\u4e00\u9053\u7ecf\u5178\u7684\u73af\u5f62 DP \u95ee\u9898\u3002\n\n\u73af\u5f62 DP \u7684\u4e00\u79cd\u7ecf\u5178\u89e3\u51b3\u65b9\u6848\u662f\u9009\u62e9\u4e00\u4e2a\u4f4d\u7f6e\u628a\u73af\u65ad\u5f00\uff0c\u53d8\u6210\u7ebf\u6027\u7ed3\u6784\u8fdb\u884c\u8ba1\u7b97\u3002\n\n\u5bf9\u4e8e\u8fd9\u9053\u9898\uff0c\u6211\u4eec\u53ef\u4ee5\u5148\u8003\u8651\u7b2c N \u4e2a\u5c0f\u65f6\u548c\u4e0b\u4e00\u5929\u7684\u7b2c 1 \u4e2a\u5c0f\u65f6\u4e0d\u76f8\u8fde\u7684\u60c5\u51b5\uff0c\u8fd9\u6837\u7740\u5c31\u6210\u4e86\u4e00\u9053\u7ebf\u6027 DP\uff1a\n\n\u8bbe $F_{i,j,0/1}$ \u8868\u793a\u524d $i$ \u4e2a\u5c0f\u65f6\u4f11\u606f\u4e86 $j$ \u4e2a\u5c0f\u65f6\uff0c\u7b2c $i$ \u4e2a\u5c0f\u65f6 \u6ca1\u6709\u4f11\u606f/\u6b63\u5728\u4f11\u606f\u3002\n\n\u5219\u6709\u72b6\u6001\u8f6c\u79fb\u65b9\u7a0b\uff1a\n\n$$F_{i,j,0}=max(F_{i-1,j,0},F_{i-1,j,1})$$\n$$F_{i,j,1}=max(F_{i-1,j-1,0},F_{i-1,j-1,1}+U_i)$$\n\n\u5728\u8fd9\u4e2a\u7b80\u5316\u7684\u95ee\u9898\u4e2d\uff0c\u7b2c 1 \u4e2a\u5c0f\u65f6\u4e00\u5b9a\u662f\u6bcf\u5929\u7684\u5f00\u59cb\uff0c\u4e0d\u53ef\u80fd\u5904\u4e8e\u719f\u7761\u72b6\u6001\u3002  \n\u56e0\u6b64 DP \u7684\u521d\u503c\u4e3a $F_{1,0,0}=0,F_{1,1,1}=0$\uff0c\u5176\u4f59\u4e3a $-inf$\u3002\n\n\u76ee\u6807\u4e3a\uff1a$max(F_{N,B,0},F_{N,B,1})$\u3002\n\n\u6211\u4eec\u53d1\u73b0\u6b64\u65f6\u7684\u7ebf\u6027 DP \u95ee\u9898\u53ea\u6bd4\u539f\u6765\u7684\u73af\u5f62 DP \u95ee\u9898\u5c11\u4e00\u79cd\u60c5\u51b5\uff0c\u5373\u5728\u7b2c 1 \u4e2a\u5c0f\u65f6\u719f\u7761\uff0c\u5e76\u4e14\u6b64\u65f6\u53ef\u4ee5\u83b7\u5f97\u4f53\u529b\uff0c\u4e5f\u5c31\u662f\u8bf4\u7b2c N \u5929\u4e5f\u5fc5\u987b\u5728\u4f11\u606f\u3002  \n\u4e3a\u8fbe\u5230\u8fd9\u4e2a\u76ee\u7684\u6211\u4eec\u53ea\u9700\u8981\u5f3a\u5236\u4fee\u6539\u521d\u503c $F_{1,1,1}=U_1$ \uff0c\u5176\u4f59\u503c\u4e3a $-inf$ ,\u6240\u6c42\u76ee\u6807\u4e3a $F_{N,B,1}$ \u5373\u53ef\u3002\n\n\u6700\u7ec8\u7b54\u6848\u4e3a\u4e24\u6b21 DP \u7ed3\u679c\u7684\u8f83\u4f18\u8005\u3002\n\n\u672c\u8d28\u89e3\u6cd5\u5c31\u662f\u628a\u95ee\u9898\u62c6\u6210\u4e24\u90e8\u5206\u8fdb\u884c\u6c42\u89e3\u3002\u7b2c\u4e00\u90e8\u5206\u4e0d\u53ef\u80fd\u5728\u7b2c 1 \u5c0f\u65f6\u6062\u590d\u4f53\u529b\uff0c\u800c\u7b2c\u4e8c\u90e8\u5206\u5f3a\u5236\u5728\u7b2c 1 \u5c0f\u65f6\u83b7\u5f97\u4f53\u529b\u3002\n## Code\n```cpp\n#include <iostream>\n#include <cstdio>\n#include <cstring>\n#define inf 0x7fffffff\nusing namespace std;\nint n,B,a[3831],f[3831][3831][2];\nvoid dp()//DP\u90e8\u5206\n{\n\tfor(int i=2; i<=n; i++)\n\t\tfor(int j=0; j<=B; j++) {\n\t\t\tf[i][j][0]=max(f[i-1][j][0],f[i-1][j][1]);//\u72b6\u6001\u8f6c\u79fb\u65b9\u7a0b\n\t\t\tif(j-1>=0) {\n\t\t\t\tf[i][j][1]=max(f[i-1][j-1][0],f[i-1][j-1][1]+a[i]);\n\t\t\t}\n\t\t}\n}\nint main() {\n\tcin>>n>>B;\n\tfor(int i=1; i<=n; i++)\n\t\tcin>>a[i];\n\tmemset(f,-0x3f,sizeof(f));//\u7b2c\u4e00\u6b21DP\u8d4b\u521d\u503c\n\tf[1][0][0]=0;\n\tf[1][1][1]=0;\n\tdp();//\u7b2c\u4e00\u6b21DP\n\tint ans=max(f[n][B][1],f[n][B][0]);\n\tmemset(f,-0x3f,sizeof(f));//\u7b2c\u4e8c\u6b21DP\u8d4b\u521d\u503c\n\tf[1][1][1]=a[1];\n\tdp();//\u7b2c\u4e8c\u6b21DP\n\tcout<<max(ans,f[n][B][1]);//\u8f93\u51fa\u4e24\u6b21DP\u7ed3\u679c\u8f83\u4f18\u8005\n\treturn 0;\n}\n```\n",
        "postTime": 1633339971,
        "uid": 482082,
        "name": "Mortis_Vampire",
        "ccfLevel": 4,
        "title": "\u9898\u89e3 P6064 [USACO05JAN]Naptime G"
    },
    {
        "content": "## \u9898\u76ee\u5206\u6790\uff1a\n\n\u9996\u5148\u662f\u4e00\u4e2a\u7ebf\u6027 DP,\u8fd9\u4e00\u70b9\u5f88\u91cd\u8981\uff0c\u6211\u90fd\u4e0d\u77e5\u9053\u4e00\u5f00\u59cb\u6211\u4e3a\u4ec0\u4e48\u60f3\u6210\u4e86\u60f3\u6210\u4e86\u5355\u8c03\u961f\u5217\u4f18\u5316\u7684\u795e\u4ed9\u533a\u95f4 DP\uff0c\u8fd9\u5c31\u6ca1\u6551\u4e86\u3002\n\n\u8003\u8651\u4e00\u822c\u60c5\u51b5\uff0c\u5982\u679c\u4e0d\u662f\u5728\u73af\u4e0a\u7684\u8bdd\uff0cDP \u72b6\u6001\u662f\u5f88\u660e\u663e\u7684\uff1a\n\n\u9996\u5148\u4e00\u5b9a\u8981\u8bb0\u5f55\u76ee\u524d\u7684\u7b54\u6848\u662f\u5230\u54ea\u4e3a\u6b62\u7684\u3002\n\n\u5176\u6b21\uff0c\u5fc5\u7136\u4f1a\u8bb0\u5f55\u5f53\u524d\u70b9\u662f\u5426\u5728\u7761\u3002\n\n\u6700\u540e\uff0c\u5fc5\u4e0d\u53ef\u5c11\u7684\u5df2\u7ecf\u7761\u4e86\u4e86\u591a\u957f\u7684\u65f6\u95f4\u3002\n\n\u7efc\u4e0a\u72b6\u6001\u4fbf\u662f\u4e00\u4e2a\u4e09\u7ef4\u6570\u7ec4 $dp[N][B][2]$\u3002\n\n\u7b2c\u4e00\u7ef4\u8bb0\u5f55\u5904\u7406\u5230\u90a3\u4e2a\u70b9\uff0c\u7b2c\u4e8c\u7ef4\u7eaa\u5f55\u5df2\u7761\u7684\u65f6\u95f4\uff0c\u7b2c\u4e09\u4f4d\u5c31\u662f\u662f\u5426\u5728\u7761\u3002\n\n\u72b6dp\u6001\u51fa\u6765\u4e86,\u8f6c\u79fb\u65b9\u7a0b\u4e5f\u5c31\u6bd4\u8f83\u663e\u7136:\n$$dp[i][j][x]=\n\\begin{cases}\n&max\\left(dp[i-1][j][0],dp[i-1][j][1])\\right) &x = 0\\\\\n&max\\left(dp[i-1][j-1][0],dp[i-1][j-1][1]+a[j])\\right)&x = 1\\\\   \n\\end{cases}$$\n\n\u89c2\u5bdf\u5230\u6bcf\u4e00\u5c42\u72b6\u6001\u53ea\u4f1a\u4ece\u4e0a\u4e00\u5c42\u8f6c\u79fb\uff0c\u6545\u53ef\u4ee5\u4f7f\u7528\u6eda\u52a8\u6570\u7ec4\u6765\u8fdb\u4e00\u6b65\u4f18\u5316\u7a7a\u95f4\u3002\n\n\u63a5\u4e0b\u6765\u56de\u5230\u539f\u95ee\u9898,\u8003\u8651\u5904\u7406\u73af\u4e0a\u95ee\u9898\u7684\u529e\u6cd5\uff1a\n- \u500d\u957f\n- \u5f3a\u5236\u94fe\u63a5\n\n\u4ed4\u7ec6\u8003\u8651\u53d1\u73b0\u500d\u957f\u5e76\u4e0d\u597d\u5904\u7406\uff0c\u7531\u8f6c\u79fb\u7684\u4e00\u4e9b\u95ee\u9898\u5bfc\u81f4\u5f88\u96be\u7edf\u8ba1\u7b54\u6848\u3002\n\n\u6545\u4f7f\u7528\u5f3a\u5236\u94fe\u63a5\u3002\n\n\u505a\u5b8c\u4e0a\u9762\u5e8f\u5217\u4e0a\u7684 DP \u540e\uff0c\u5f3a\u5236\u9009\u62e9 1 \u53f7\u70b9\u7761\u89c9\uff0c\u518d DP \u4e00\u6b21\uff0c\u4f46\u6ce8\u610f\uff0c\u6b64\u65f6\u7edf\u8ba1\u7684\u7b54\u6848\u5c31\u53ea\u80fd\u662f $dp[n][B][1]$\u3002\n\nCode:\n~~~c++\n\\\\ Code by \u4e91\u5c81\u6708\u4e66\n# include <ctime>\n# include <cmath>\n# include <cstdio>\n# include <cstdlib>\n# include <cstring>\n# include <algorithm>\n# define N 3830\n# define max std::max\n\ninline int Read()\n{\n    register int x = 0;char ch = getchar();\n\n    while(ch < '0' || ch > '9')ch = getchar();\n\n    while(ch >= '0' && ch <= '9'){x = x*10+(ch^48);ch = getchar();}\n\n    return x;\n}\n\ninline int Max(const int x,const int y){return x > y ? x : y;}\ninline int Min(const int x,const int y){return x < y ? x : y;}\n\nint n,m,f[2][N+5][2],a[N+5],ans;\n\nvoid DP()\n{\n    for(int i = 2; i <= n ; ++i)\n\t{\n\t\tf[i&1][0][0] = f[(i^1)&1][0][0];\n\t\tfor(int j = 1; j <= m ; ++j)\n        {\n            f[i&1][j][0] = max(f[(i^1)&1][j][0],f[(i^1)&1][j][1]);\n            f[i&1][j][1] = max(f[(i^1)&1][j-1][0],f[(i^1)&1][j-1][1]+a[i]);\n        }\n\t}\n}\n\nint main()\n{\n    n = Read();m = Read();\n    for(int i = 1; i <= n ; ++i) a[i] = Read();\n    if(m == 0) return printf(\"0\\n\"),0;\n    memset(f,-0x3f,sizeof(f));\n    f[1][0][0] = f[1][1][1] = 0;//\u6ce8\u610f\u4e00\u4e0b\u521d\u59cb\u72b6\u6001\u7684\u5904\u7406\n    DP();\n    ans = max(f[n&1][m][0],f[n&1][m][1]);\n    memset(f,-0x3f,sizeof(f));\n    f[1][1][1] = a[1];\n    DP();\n    ans = max(ans,f[n&1][m][1]);\n    printf(\"%d\\n\",ans);\n    return 0;\n}\n~~~",
        "postTime": 1600001477,
        "uid": 222127,
        "name": "\u4e91\u5c81\u6708\u4e66",
        "ccfLevel": 0,
        "title": "\u9898\u89e3 P6064 \u3010[USACO05JAN]Naptime G\u3011"
    },
    {
        "content": "[P6064 [USACO05JAN]Naptime G](https://www.luogu.com.cn/problem/P6064)\n\n\u7b97\u6cd5\uff1a\u7ebf\u6027 $\\operatorname{DP}$\n\n### $step~1$ \uff1a\u5217\u51fa\u57fa\u7840\u8f6c\u79fb\u65b9\u7a0b\n\n\u5148\u4e0d\u8003\u8651\u7b2c $n$ \u4e2a\u5c0f\u65f6\u4e0e\u6b21\u65e5\u7b2c $1$ \u4e2a\u5c0f\u65f6\u8fde\u7eed \u3002\n\n\u8bbe $dp[i][j][0/1]$ \u8868\u793a\u5728\u7b2c $i$ \u4e2a\u5c0f\u65f6\uff0c\u5df2\u7ecf\u5728\u5e8a\u4e0a\u8eba\u4e86 $j$ \u4e2a\u5c0f\u65f6\uff0c$0$ \u8868\u793a\u8fd9\u4e2a\u5c0f\u65f6\u6ca1\u5728\u5e8a\u4e0a\uff0c$1$ \u8868\u793a\u8fd9\u4e2a\u5c0f\u65f6\u6b63\u8eba\u5728\u5e8a\u4e0a \u3002\n\n\u8f6c\u79fb\u65b9\u7a0b\uff1a\uff08 \u521d\u59cb\u503c $dp[1][0][0]=dp[1][1][1]=0$ \uff0c\u5176\u4ed6\u4e3a $-\\inf$ \uff09\n\n$$\\begin{cases}dp[i][j][0]=\\max{\\{dp[i-1][j][0],dp[i-1][j][1]\\}}\\\\dp[i][j][1]=\\max{\\{dp[i-1][j-1][0],dp[i-1][j-1][1]+u[i]\\}}\\end{cases}$$\n\n\u76ee\u6807\uff1a$\\min{\\{dp[n][b][0],dp[n][b][1]\\}}$ \u3002\n\n### $step~2$ \uff1a\u5b8c\u5584\u8f6c\u79fb\u65b9\u7a0b\n\n\u8003\u8651\u7b2c $n$ \u4e2a\u5c0f\u65f6\u4e0e\u6b21\u65e5\u7b2c $1$ \u4e2a\u5c0f\u65f6\u8fde\u7eed \uff0c\u5373\u5f3a\u5236\u7b2c\u7b2c $n$ \u4e2a\u5c0f\u65f6\u7761\u89c9 \u3002\n\n\u521d\u59cb\u503c\uff1a$dp[1][0][0]=0,dp[1][1][1]=u[1]$ \uff0c\u5176\u4ed6\u4e3a $-\\inf$ \u3002\n\n\u76ee\u6807\uff1a$dp[n][m][1]$ \u3002\n\n\u6700\u7ec8\u7b54\u6848\u4e3a\u4e24\u79cd\u60c5\u51b5\u7684\u8f83\u5927\u503c\u3002\n\n~~\u5b8c\u6574~~\u4ee3\u7801\uff1a\n\n```cpp\n#define inf 0x7f7f7f7f\n#define Maxn 3835\nint n,b,ans,a[Maxn],dp[Maxn][Maxn][2];\n\n// \u4e00\u4e0b\u4ee3\u7801\u7247\u6bb5\u63d2\u5165\u5728 main \u51fd\u6570\u4e2d \nn=rd(),b=rd();\nfor(int i=1;i<=n;i++) a[i]=rd();\nmemset(dp,-inf,sizeof(dp)),dp[1][1][1]=dp[1][0][0]=0;\nfor(int i=2;i<=n;i++)\n{\n \t dp[i][0][0]=dp[i-1][0][0];\n\t for(int j=1;j<=b;j++)\n\t {\n\t \t dp[i][j][0]=max(dp[i-1][j][1],dp[i-1][j][0]);\n\t \t dp[i][j][1]=max(dp[i-1][j-1][0],dp[i-1][j-1][1]+a[i]);\n\t }\n}\nans=max(dp[n][b][0],dp[n][b][1]);\nmemset(dp,-inf,sizeof(dp)),dp[1][1][1]=a[1],dp[1][0][0]=0;\nfor(int i=2;i<=n;i++)\n{\n \t dp[i][0][0]=dp[i-1][0][0];\n \t for(int j=1;j<=b;j++)\n \t {\n \t \t dp[i][j][0]=max(dp[i-1][j][1],dp[i-1][j][0]);\n \t \t dp[i][j][1]=max(dp[i-1][j-1][0],dp[i-1][j-1][1]+a[i]);\n\t }\n}\nans=max(ans,dp[n][b][1]);\nprintf(\"%d\\n\",ans);\n```\n\n[$\\leftarrow$ \u6211\u7684 $\\operatorname{DP}$ \u6742\u9898\u4e13\u9898](https://www.luogu.com.cn/blog/EricQian/dp-za-ti)",
        "postTime": 1603538576,
        "uid": 113073,
        "name": "EricQian",
        "ccfLevel": 7,
        "title": "P6064 [USACO05JAN]Naptime G"
    },
    {
        "content": "## \u3010\u5206\u6790\u8fc7\u7a0b\u3011\n\n\u6211\u4eec\u53ef\u4ee5\u7528\u4e00\u4e2a\u4e09\u7ef4\u6570\u7ec4 $f_{i,o,p}$ \u6765\u8868\u793a\u72b6\u6001\n\n\u5176\u4e2d $i$ \u8868\u793a\u7ecf\u8fc7\u4e86\u7684\u65f6\u95f4\u6bb5\uff0c$o$ \u8868\u793a\u5df2\u7ecf\u7761\u4e86 $o$ \u4e2a\u65f6\u95f4\u6bb5\uff0c$p$ \u8868\u793a\u8fd9\u4e2a\u65f6\u95f4\u6bb5\u6709\u6ca1\u6709\u5728\u7761\u89c9\n\n**\u90a3\u4e48\u5bf9\u4e8e\u4e00\u4e2a\u65f6\u95f4\u6bb5\u6709\u4e24\u79cd\u51b3\u7b56\uff1a\u7761\u89c9\u6216\u662f\u4e0d\u7761\u89c9**\n\n- \u6ca1\u6709\u7761\u89c9\uff0c\u4ece\u4e0a\u4e2a\u65f6\u95f4\u6bb5\u53d6\u6700\u5927\u503c\n\n- \u7761\u89c9\uff0c\u4e0a\u4e00\u6bb5\u65f6\u95f4\u53c8\u6709\u4e24\u79cd\u72b6\u51b5\uff1a\u5728\u7761\u89c9\u6216\u662f\u6ca1\u6709\u7761\u89c9\uff1b\u5728\u7761\u89c9\u5373\u53ef\u83b7\u5f97\u6548\u76ca\u503c $v_i$\n\n\u6240\u4ee5\u6211\u4eec\u53ef\u4ee5\u63a8\u51fa\u8f6c\u79fb\u65b9\u7a0b\uff1a\n\n$f_{i,o,0}=\\max(f_{i-1,o,0},f_{i-1,o,1})$\n\n$f_{i,o,1}=\\max(f_{i-1,o-1,0},f_{i-1,o-1,1}+v_i)$\n\n\u56e0\u4e3a\u6b64\u9898\u662f\u4e00\u4e2a\u73af\u5f62\u52a8\u6001\u89c4\u5212\uff0c\u6240\u4ee5\u6211\u4eec\u9009\u62e9**\u5f3a\u5236\u65ad\u73af\u7136\u540e\u5f3a\u5236\u8fde\u73af**\u8fdb\u884c\u4e24\u6b21\u52a8\u6001\u89c4\u5212\u6765\u6d88\u9664\u540e\u6548\u6027\n\n\u65ad\u73af\uff0c\u610f\u5373\u5728\u65f6\u95f4 $N$ \u4e0d\u7761\u89c9\uff0c\u6240\u4ee5\u989d\u5916\u521d\u59cb\u5316\u4e3a $f_{1,1,1}=0$\n\n\u8fde\u73af\uff0c\u610f\u5373\u5728\u65f6\u95f4 $N$ \u548c\u6b21\u65e5\u65f6\u95f4 $1$ \u7684\u65f6\u5019\u5f3a\u5236\u7761\u89c9\uff0c\u6240\u4ee5\u989d\u5916\u521d\u59cb\u5316\u4e3a $f_{1,1,1}=v_1$\uff0c\u7edf\u8ba1\u7b54\u6848\u7684\u65f6\u5019\u4e3a $ans=\\max(ans,f_{n,m,1})$\n\n## \u3010\u4ee3\u7801\u5b9e\u73b0\u3011\n\n```\n#include<iostream>\n#include<cstring>\n#define N 4000\n#define set(f) memset(f,-0x3f,sizeof(f))\n#define cl(a) for(int i=1;i<=n;i++) a[i][0][0]=0;\nusing namespace std;\nint n,in[N],b,ans,f[N][N][2];\nsigned main(){\n\tcin>>n>>b;\n\tfor(int i=1;i<=n;i++){\n\t\tcin>>in[i];\n\t}\n\tset(f);cl(f);\n\tf[1][1][1]=0;\n\tfor(int i=2;i<=n;i++){\n\t\tfor(int o=1;o<=i;o++){\n\t\t\tf[i][o][0]=max(f[i-1][o][0],f[i-1][o][1]);\n\t\t\tf[i][o][1]=max(f[i-1][o-1][1]+in[i],f[i-1][o-1][0]);\n\t\t}\n\t}\n\tans=max(f[n][b][0],f[n][b][1]);\n\tset(f);cl(f);\n\tf[1][1][1]=in[1];\n\tfor(int i=2;i<=n;i++){\n\t\tfor(int o=1;o<=i;o++){\n\t\t\tf[i][o][0]=max(f[i-1][o][0],f[i-1][o][1]);\n\t\t\tf[i][o][1]=max(f[i-1][o-1][1]+in[i],f[i-1][o-1][0]);\n\t\t}\n\t}\n\tcout<<max(ans,f[n][b][1]);\n}\n```",
        "postTime": 1601004746,
        "uid": 215573,
        "name": "zythonc",
        "ccfLevel": 7,
        "title": "\u9898\u89e3 P6064 \u3010[USACO05JAN]Naptime G\u3011"
    },
    {
        "content": "------------\n\n\n**\u661f\u5f71\u843d\u4e5d\u5929\uff0c\u9c7c\u96c1\u821e\u5343\u5f26\u3002\u4f46\u4e3a\u541b\u6c89\u541f\uff0c\u843d\u65e5\u5929\u6daf\u5706\u3002**\n\n------------\n[[\u9898\u76ee\u4f20\u9001\u95e8]](https://www.luogu.com.cn/problem/P6064)\n\n\u5148\u8003\u8651\u82e5\u4e0d\u662f\u73af\u7684\u60c5\u51b5\n\n\u8bbe\u72b6\u6001\u4e3a$dp[i][j][0/1]$\uff1a\n\n$dp[i][j][0]$\u8868\u793a\u524d$i$\u6bb5\u7761\u4e86$j$\u6bb5\u4e14**\u7b2c**$i$**\u6bb5\u6ca1\u7761**\u524d$i$\u6bb5\u7684\u6700\u5927\u6548\u7528\u503c\n\n$dp[i][j][1]$\u8868\u793a\u524d$i$\u6bb5\u7761\u4e86$j$\u6bb5\u4e14**\u7b2c**$i$**\u6bb5\u7761\u4e86**\u524d$i$\u6bb5\u7684\u6700\u5927\u6548\u7528\u503c\n\n\u90a3\u4e48**\u72b6\u6001\u8f6c\u79fb\u65b9\u7a0b**\u5373\u4e3a\uff1a\n$$\n\tdp_{i,j,0}=max(dp_{i-1,j,0},dp_{i-1,j,1})$$\n$$\n\tdp_{i,j,1}=max(dp_{i-1,j-1,0}+0,dp_{i-1,j-1,1}+a_{i})$$\n    \n$dp_{i,j,0/1}$\u7684\u521d\u503c\u4e3a-INF\n\n\u90a3\u4e48**\u5bf9\u4e8e\u73af**\uff0c\u53ea\u9700\u8981\u5f3a\u5236\u8fde\u63a5\u7b2c$n$\u6bb5\u4e0e\u7b2c$1$\u6bb5\n\n\u5373\uff1a\u5c06$dp_{1,0,0}$\u7684\u521d\u503c\u8d4b\u4e3a$a_{1}$\u5373\u53ef\n\n## Code\n\n```cpp\n#include<bits/stdc++.h>\n#define FQ(i,a,b) for(register int i=a;i<=b;i++)\n#define prf printf\n#define scf scanf\n#define ll long long\nusing namespace std;\nint INF;\nconst int N=3835;\nint n,m,ans,a[N],F[N][N][2];\nll read()\n{\n\tll x=0,f=1;char ch=getchar();\n\twhile(ch<'0'||ch>'9'){if(ch=='-')f=-1;ch=getchar();}\n\twhile(ch>='0'&&ch<='9'){x=x*10+ch-'0';ch=getchar();}\n\treturn x*f;\n}\nint main()\n{\n\tINF=-128/2;\n\tn=read(),m=read();memset(F,INF,sizeof(F));\n\tfor(int i=1;i<=n;i++)a[i]=read();\n\tfor(int i=1;i<=n;i++)F[i][0][0]=0;F[1][1][1]=0;\n\tfor(int i=2;i<=n;i++)\n\t\tfor(int j=1;j<=m;j++)\n\t\t{\t\t\n\t\t\tF[i][j][0]=max(F[i-1][j][0],F[i-1][j][1]);\t\t\n\t\t\tF[i][j][1]=max(F[i-1][j-1][0]+0,F[i-1][j-1][1]+a[i]);\t\t\n\t\t}\t\n\tans=max(F[n][m][1],F[n][m][0]);\t\n\tmemset(F,INF,sizeof(F));\n\tfor(int i=1;i<=n;i++)F[i][0][0]=0;F[1][1][1]=a[1];\n\tfor(int i=2;i<=n;i++)\n\t\tfor(int j=1;j<=m;j++)\n\t\t{\t\n\t\t\tF[i][j][0]=max(F[i-1][j][0],F[i-1][j][1]);\t\n\t\t\tF[i][j][1]=max(F[i-1][j-1][0]+0/*\u4e0d\u8ba1i\u7684\u6548\u7528\u503c*/,F[i-1][j-1][1]+a[i]);\t\n\t\t}\n\tans=max(ans,F[n][m][1]);\n\tprintf(\"%d\\n\",ans);\n\treturn 0;\t\n} \n```\n",
        "postTime": 1600693009,
        "uid": 116374,
        "name": "\u6708\u96e9\u00b7\u8587\u5aed",
        "ccfLevel": 4,
        "title": "P6064 [USACO05JAN] \u300cNaptime\u300d"
    }
]