[
    {
        "content": "\u4e00\u4e2a\u91cd\u8981\u7684\u89c2\u5bdf\uff1a\u5c06 $1$ \u8c03\u6574\u5230\u9996\u4f4d\u4e4b\u540e\uff0c\u5176\u4f59\u5143\u7d20\u53ef\u4ee5\u4efb\u610f\u4ea4\u6362\u4f4d\u7f6e\u3002\n\n\u4ee4 $q$ \u4e3a $p$ \u7684\u9006\uff0c\u8bb0 $f(p)$ \u4e3a $p$ \u7684\u7f6e\u6362\u73af\u4e2a\u6570\u3002\n\n\u4e00\u4e2a\u7ecf\u5178\u7684\u7ed3\u8bba\uff1a\u5bf9\u4e8e\u4e00\u4e2a $1\\sim n$ \u7684\u6392\u5217 $p$\uff0c\u4e00\u6b21\u64cd\u4f5c\u53ef\u4ee5\u4ea4\u6362\u5176\u4e2d\u4efb\u610f\u4e24\u4e2a\u6570\u7684\u4f4d\u7f6e\uff0c\u5219\u81f3\u5c11\u9700\u8981 $n\u2212f(p)$ \u6b21\u64cd\u4f5c\u624d\u80fd\u5c06 $p$ \u5347\u5e8f\u6392\u5217\uff0c\u56e0\u4e3a\u6bcf\u6b21\u4ea4\u6362\u6700\u591a\u4f7f $f(p)$ \u51cf\u5c11 $1$\u3002\u4e00\u79cd\u53ef\u884c\u7684\u4ea4\u6362\u65b9\u6848\u662f\uff0c\u4ece\u5c0f\u5230\u5927\u679a\u4e3e $i$\uff0c\u82e5 $p_i\\neq i$\uff0c\u5219\u4ea4\u6362 $p_i$ \u548c $p_{q_i}$\u3002\n\n\u63a5\u4e0b\u6765\u8003\u8651\u5982\u4f55\u5728\u5c06 $1$ \u7528\u5c3d\u91cf\u5c11\u7684\u64cd\u4f5c\u6b21\u6570\u8c03\u6574\u5230\u9996\u4f4d\u7684\u540c\u65f6\uff0c\u4f7f $f(p)$ \u5c3d\u91cf\u5927\u3002\n\n\u4e0b\u9762\u9ed8\u8ba4\u7b2c $(i+1)$ \u4e2a Case \u4e0d\u5305\u542b\u7b2c $1\\sim i$ \u4e2a Case\u3002\n\n### Case 1\uff1a $n\\le 3$\n\n\u7279\u5224\u5373\u53ef\u3002\n\n### Case 2\uff1a $q_1=n$\n\n\u5bb9\u6613\u53d1\u73b0\u8fd9\u79cd\u60c5\u51b5\u4e0b\u6211\u4eec\u65e0\u6cd5\u79fb\u52a8 $1$ \u7684\u4f4d\u7f6e\uff0c\u6545\u8f93\u51fa `-1`\u3002\n\n### Case 3\uff1a $q_1=1$\n\n\u5bb9\u6613\u53d1\u73b0\u8fd9\u79cd\u60c5\u51b5\u4e0b\u6211\u4eec\u53ef\u4ee5\u5229\u7528 $1$ \u4ea4\u6362\u6392\u5217\u4e2d\u9664\u4e86 $1$ \u7684\u4efb\u610f\u4e24\u4e2a\u6570\uff0c\u6545\u6b64\u65f6\u4ea4\u6362\u7684\u6700\u5c11\u6b21\u6570\u4e3a $n-f(p)\\le n$\u3002\n\n### Case 4\uff1a $\\exists \\ q_1<i\\le n,p_i<p_1$\n\n\u8fdb\u884c\u4e00\u6b21 $(1,q_1,i)$ \u7684\u64cd\u4f5c\u5373\u53ef\u8f6c\u6362\u4e3a Case 3\uff0c\u5bb9\u6613\u53d1\u73b0\u603b\u6700\u5c11\u64cd\u4f5c\u6b21\u6570\u4ecd\u4e3a $n-f(p)\\le n$\u3002\n\n### Case 5\uff1a $p_1\\ge 3$\n\n\u7531\u4e8e $1$ \u53f3\u8fb9\u7684\u6570\u5747\u6bd4 $p_1$ \u5927\uff0c\u6545 $1$ \u5de6\u8fb9\u4e00\u5b9a\u5b58\u5728\u4e00\u4e2a $i\\ (2\\le i<q_1)$ \u4f7f\u5f97 $p_i<p_1$\uff0c\u8fdb\u884c\u4e00\u6b21 $(1,i,n)$ \u7684\u64cd\u4f5c\u5373\u53ef\u8f6c\u6362\u4e3a  Case 4\u3002\u7531\u4e8e\u4e24\u6b21\u64cd\u4f5c\u540e $p_1=1$\uff0c\u6545\u64cd\u4f5c\u6b21\u6570 $\\le 2+(n-2)=n$\u3002\n\n### Case 6\uff1a $p_1=2,p_2=1,p_i=i\\ (3\\le i\\le n)$\n\n\u6b64\u79cd\u60c5\u51b5\u4e0b\u7684\u6700\u5c11\u64cd\u4f5c\u6b21\u6570\u4e3a $5$ \u6b21\uff0c\u4e00\u79cd\u53ef\u884c\u7684\u65b9\u6848\u4e3a $(1,2,3),(1,2,3),(1,2,4),(1,3,4),(1,2,4)$\u3002\u6ce8\u610f\u6b64\u65f6\u82e5 $n=L=4$ \u9700\u8f93\u51fa `-1`\u3002\n\n### Case 7\uff1a $p_1=2,p_2=1$\n\n\u627e\u5230\u4e00\u4e2a $i\\ (3\\le i<n)$ \u6ee1\u8db3 $p_i>p_{i+1}$\uff0c\u5219\u6211\u4eec\u53ef\u4ee5\u8fdb\u884c $(1,2,i),(1,2,i),(1,i,i+1)$ \u4e09\u6b21\u64cd\u4f5c\u4f7f\u5f97 $p_1=1,p_2=2$\uff0c\u6545\u64cd\u4f5c\u6b21\u6570 $\\le 3+(n-3)=n$\u3002\n\n### Case 8\uff1a$p_1=2$\n\n\u82e5 $q_n=2$\uff0c\u8fdb\u884c $(1,2,q_1),(1,q_1,n)$ \u4e24\u6b21\u64cd\u4f5c\uff0c\u5426\u5219\u8fdb\u884c $(1,2,q_n),(1,2,q_1),(1,q_1,n)$ \u4e09\u6b21\u64cd\u4f5c\uff0c\u7531\u4e8e\u81f3\u591a\u4e09\u6b21\u64cd\u4f5c\u540e $p_1=1,p_2=2$\uff0c\u6545\u64cd\u4f5c\u6b21\u6570 $\\le 3+(n-3)=n$\u3002\n\n\u65f6\u95f4\u590d\u6742\u5ea6\u4e3a $O(\\sum n)$\u3002\n\n```cpp\n#include<bits/stdc++.h>\nusing namespace std;\nint t,n,l,cnt,p[2000009],q[2000009];\nstruct st{int x,y,z;}ans[2000009];\ninline int read(){\n\tint s = 0,w = 1;\n\tchar ch = getchar();\n\twhile (ch > '9' || ch < '0'){ if (ch == '-') w = -1; ch = getchar();}\n\twhile (ch <= '9' && ch >= '0') s = (s << 1) + (s << 3) + (ch ^ 48),ch = getchar();\n\treturn s * w;\n}\nvoid print(){\n\tif (cnt > l){puts(\"-1\"); return;}\n\tprintf(\"%d\\n\",cnt);\n\tfor (int i = 1;i <= cnt;i += 1){\n\t\tprintf(\"%d %d %d\\n\",ans[i].x,ans[i].y,ans[i].z);\n\t}\n}\nvoid add(int x,int y,int z){\n\tif (p[x] > p[z]) swap(p[x],p[y]),swap(q[p[x]],q[p[y]]);\n\telse swap(p[y],p[z]),swap(q[p[y]],q[p[z]]);\n\tans[++ cnt] = (st){x,y,z};\n}\nvoid swapsort(){\n\tfor (int i = 1;i <= n;i += 1) if (q[i] != i) add(1,min(i,q[i]),max(i,q[i]));\n}\nvoid work(){\n\tif (n == 1) return;\n\tif (q[1] == n){cnt = 1e9; return;}\n\tif (n == 2) return;\n\tif (q[1] == 1){swapsort(); return;}\n\tif (n == 3){\n\t\tif (p[1] == 2) cnt = 1e9;\n\t\telse add(1,2,3),add(1,2,3);\n\t\treturn;\n\t}\n\tint pos = q[1];\n\tfor (int i = pos + 1;i <= n;i += 1) if (p[i] < p[1]){\n\t\tadd(1,pos,i),swapsort();\n\t\treturn;\n\t}\n\tif (p[1] >= 3){\n\t\tfor (int i = 2;i < pos;i += 1) if (p[i] < p[1]){\n\t\t\tadd(1,i,n),add(1,pos,n),swapsort();\n\t\t\treturn;\n\t\t}\n\t\treturn;\n\t}\n\tif (p[2] == 1){\n\t\tfor (int i = 3;i < n;i += 1) if (p[i] > p[i + 1]){\n\t\t\tadd(1,2,i),add(1,2,i),add(1,i,i + 1),swapsort();\n\t\t\treturn;\n\t\t}\n\t\tadd(1,2,3),add(1,2,3),add(1,2,4),add(1,3,4),add(1,2,4);\n\t\treturn;\n\t}\n\tif (q[n] > 2) add(1,2,q[n]);\n\tadd(1,2,pos),add(1,pos,n),swapsort();\n}\nint main(){\n\tt = read();\n\twhile (t --){\n\t\tn = read(),l = read(),cnt = 0;\n\t\tfor (int i = 1;i <= n;i += 1) p[i] = read();\n\t\tfor (int i = 1;i <= n;i += 1) q[p[i]] = i;\n\t\twork(),print();\n\t}\n\treturn 0;\n}\n```\n",
        "postTime": 1684158544,
        "uid": 322075,
        "name": "Ecrade_",
        "ccfLevel": 7,
        "title": "\u300cRHOI-1\u300d\u4f3c\u66fe\u76f8\u8bc6\u71d5\u5f52\u6765 \u9898\u89e3"
    },
    {
        "content": "[\u6d1b\u8c37\u9898\u9762\u4f20\u9001\u95e8](https://www.luogu.com.cn/problem/P9347)\u3002\n\n\u9898\u610f\uff1a\n\n* \u7ed9\u5b9a $n, L$ \u548c\u4e00\u4e2a\u957f\u4e3a $n$ \u7684\u6392\u5217 $p_i$\u3002\n* \u6bcf\u6b21\u64cd\u4f5c\u4e3a\u9009\u4e00\u7ec4 $1 \\le i < j < k \\le n$\uff0c\u5c06 $p_i$ \u4e0e $p_k$ \u4e2d\u8f83\u5927\u7684\u6570\u4e0e $p_j$ \u4ea4\u6362\u3002\n* \u95ee\u662f\u5426\u80fd\u5728 $L$ \u6b21\u64cd\u4f5c\u5185\u628a\u539f\u6392\u5217\u53d8\u4e3a\u6052\u7b49\u6392\u5217\u3002\n* \u591a\u7ec4\u6570\u636e\u3002$\\sum n \\le 2\\times 10^6$\uff0c$n \\le L \\le n+2$\u3002\n\n\u601d\u8def\u7b80\u5355\u7684\u5927\u529b\u5206\u7c7b\u8ba8\u8bba\u9898\u3002\n\n---\n\nSolution\uff1a\n\n$n= 1, 2, 3$ \u65f6\u53ef\u4ee5\u7279\u5224\u6389\uff0c\u4e0b\u8bbe $n \\ge 4$\u3002\u5bf9 $1 \\le i \\le n$\uff0c\u7528 $q_i$ \u8868\u793a $i$ \u5728\u7b2c\u51e0\u9879\u3002\u5f53 $p_n = 1$ \u65f6\u663e\u7136\u65e0\u89e3\u3002\u4e0b\u8003\u8651 $p_n \\neq 1$ \u7684\u60c5\u51b5\u3002\n\n\u9898\u76ee\u7ea6\u675f\u4e86 $n \\le L \\le n+2$\uff0c\u8fd9\u5f15\u5bfc\u6211\u4eec\u53bb\u601d\u8003\uff1a\u600e\u6837\u7684\u6392\u5217\u53ef\u4ee5\u5728 $n$ \u6b65\u4e4b\u5185\u53d8\u4e3a\u6052\u7b49\u6392\u5217\uff1f\u6211\u4eec\u4e0d\u59a8\u5148\u89e3\u51b3\u8fd9\u4e2a\u95ee\u9898\u3002\n\n\u6ce8\u610f\u5230\u4e00\u4e2a\u663e\u7136\u7684\u4e8b\u5b9e\uff1a**\u5f53 $p_1 = 1$ \u65f6\uff0c\u540e\u9762 $n-1$ \u9879\u53ef\u4ee5\u4efb\u610f\u4ea4\u6362**\u3002\u56e0\u6b64\u6211\u4eec\u5e0c\u671b\u5728 $2$ \u6b65\u4e4b\u5185\u628a $1$ \u64cd\u4f5c\u5230\u7b2c $1$ \u9879\u3002\n\n\u6211\u4eec\u79f0 $p_1 = 1$ \u7684\u6392\u5217\u4e3a\u201c\u597d\u6392\u5217\u201d\u3002\u8bbe $q_1 = j$\uff0c\u82e5 $\\exists\\ j< k\\le n$ \u4f7f\u5f97 $p_1 > p_k$\uff0c\u5219\u64cd\u4f5c $(1, j, k)$ \u53ef\u5f97\u5230\u597d\u6392\u5217\uff1b\u82e5 $\\forall \\  j< k \\le n, p_1 \\le p_k$\uff0c\u5f53 $p_1 \\ge 3$ \u65f6\uff0c$1<q_2<j$\uff0c\u5219\u4f9d\u6b21\u64cd\u4f5c $(1, q_2, n)$ \u548c $(1, j, n)$ \u53ef\u5f97\u5230\u597d\u6392\u5217\u3002\u6545\u6211\u4eec\u4ec5\u9700\u8003\u8651 $p_1 = 2$ \u7684\u60c5\u51b5\u3002\n\n\u53d1\u73b0 $p_1 = 2$ \u7684\u60c5\u51b5\u6bd4\u8f83\u68d8\u624b\uff0c\u56e0\u6b64\u6211\u4eec\u5e0c\u671b\u901a\u8fc7\u8f83\u5c11\u7684\u64cd\u4f5c\u8ba9 $2$ \u79fb\u5230\u5176\u5b83\u9879\uff0c\u540c\u65f6\u8ba9 $p_1$ \u5c3d\u53ef\u80fd\u5927\uff0c\u6700\u7b80\u5355\u7684\u60f3\u6cd5\u5c31\u662f\u8ba9 $2$ \u548c $n$ \u53ef\u4ee5\u4ea4\u6362\u3002\u82e5 $q_n<q_1$\uff0c\u5219\u4f9d\u6b21\u64cd\u4f5c $(1, q_n, q_1)$ \u548c $(1, q_1, n)$ \u5373\u53ef\uff1b\u82e5 $q_n > q_1$\uff0c\u5f53 $p_2 \\neq 1$ \u65f6\u4f9d\u6b21\u64cd\u4f5c $(1, 2, q_n)$\uff0c$(1, 2, q_1)$ \u548c $(1, q_1, n)$ \u5373\u53ef\u3002\u8fd9\u91cc\u770b\u4f3c\u7528\u4e86 $3$ \u6b65\uff0c\u5b9e\u5219\u5728\u64cd\u4f5c\u540e\u6709 $p_2 = 2$\uff0c\u4e3a\u4e4b\u540e\u7684\u53d8\u6362\u8282\u7701\u4e86 $1$ \u6b65\uff0c\u6240\u4ee5\u8fd9\u4e5f\u662f\u53ef\u884c\u7684\u3002\u6545\u6211\u4eec\u4ec5\u9700\u8003\u8651 $p_2 = 1$ \u7684\u60c5\u51b5\u3002\n\n\u6b64\u65f6\u6392\u5217\u4e3a $\\{2, 1, p_3, \\dots, p_n\\}$\uff0c\u8fdb\u4e00\u6b65\u6211\u4eec\u5e0c\u671b\u628a $1$ \u79fb\u5230\u975e\u7b2c\u4e8c\u9879\uff0c\u4ece\u800c\u5316\u5f52\u4e3a\u4e0a\u4e00\u79cd\u60c5\u51b5\u3002\u4e3a\u6b64\uff0c\u6211\u4eec\u627e\u6700\u5927\u7684\u4e0b\u6807 $t$ \u4f7f\u5f97 $p_t \\neq t$\uff0c\u82e5 $t \\neq 2$\uff0c\u5219\u4f9d\u6b21\u64cd\u4f5c $(1, 2, q_t)$\uff0c$(1, 2, q_1)$ \u548c $(1, q_1, t)$ \u5373\u53ef\uff1b\u82e5 $t = 2$\uff0c\u5219\u8fd9\u4e2a\u6392\u5217\u5df2\u7ecf\u552f\u4e00\u786e\u5b9a\uff1a$\\{2, 1, 3, 4, \\dots, n\\}$\uff0c\u6b64\u65f6\u4f9d\u6b21\u64cd\u4f5c $(1, 3, n)$\uff0c$(1, 2, 3)$\uff0c$(1, 2, 3)$\uff0c$(1, 3, n)$\uff0c\u6392\u5217\u53d8\u4e3a $\\{1, 2, n, 4, \\dots, n - 1, 3\\}$\u3002\u6211\u4eec\u60ca\u5947\u5730\u53d1\u73b0\u518d\u64cd\u4f5c $1$ \u6b21 $(1, 3, n)$ \u540e\u5373\u53ef\u5f97\u5230\u6052\u7b49\u6392\u5217\u3002\u6545\u5f53 $n \\ge 5$ \u65f6\u8fd9\u79cd\u6392\u5217\u65f6\u6709\u89e3\u7684\u3002\n\n\u6700\u540e\u53ea\u5269\u4e0b\u4e86 $n = 4$ \u65f6 $\\{2, 1, 3, 4\\}$ \u8fd9\u4e2a\u6392\u5217\uff0c\u624b\u52a8\u679a\u4e3e\uff08\u6216\u8005\u6572\u4e00\u4e2a\u7b80\u5355\u7684 bfs\uff09\u5c31\u53d1\u73b0\u81f3\u5c11\u9700\u8981 $5$ \u6b65\u624d\u80fd\u53d8\u6210\u6052\u7b49\u6392\u5217\u3002\n\nover. \n\n---\n\nCode\uff1a\n\n```cpp\n#include <iostream>\n#include <cstdio>\n#include <algorithm>\n#include <cstring>\n#include <cmath>\n#include <vector>\n#include <queue>\n#include <map>\n#include <set>\nusing namespace std;\n#define rep(i, x, y) for(int i = x; i <= y; ++i)\ninline int read(){\n    int x = 0, f = 1; char ch = getchar();\n    while(ch < '0' || ch > '9'){ if(ch == '-') f = -1; ch = getchar(); }\n    while(ch >= '0' && ch <= '9'){ x = x * 10 + (ch ^ 48); ch = getchar(); }\n    return x * f;\n}\nconst int N = 2000010;\nint n, m, p[N], q[N], a[N], b[N], c[N], cnt;\ninline void swap(int &x, int &y){ x ^= y ^= x ^= y; }\ninline void add(int x, int y, int z){\n\ta[++cnt] = x; b[cnt] = y; c[cnt] = z;\n\tif(p[x] > p[z]) q[p[x]] = y, q[p[y]] = x, swap(p[x], p[y]);\n\telse q[p[y]] = z, q[p[z]] = y, swap(p[y], p[z]);\n}\ninline void work(){\n\tif(p[1] == 1 && p[2] == 2 && p[3] == 3){ puts(\"0\"); }\n\tif(p[1] == 1 && p[2] == 3 && p[3] == 2){ puts(\"1\"); puts(\"1 2 3\"); }\n\tif(p[1] == 2 && p[2] == 1 && p[3] == 3){ puts(\"-1\"); }\n\tif(p[1] == 2 && p[2] == 3 && p[3] == 1){ puts(\"-1\"); }\n\tif(p[1] == 3 && p[2] == 1 && p[3] == 2){ puts(\"2\"); puts(\"1 2 3\"); puts(\"1 2 3\"); }\n\tif(p[1] == 3 && p[2] == 2 && p[3] == 1){ puts(\"-1\"); }\n}\ninline void mian(){\n\tn = read(); m = read();\n\trep(i, 1, n) p[i] = read(), q[p[i]] = i;\n\tif(n == 1){ puts(\"0\"); return; }\n\tif(n == 2){ if(p[1] == 1) puts(\"0\"); else puts(\"-1\"); return; }\n\tif(n == 3){ work(); return; }\n\tif(q[1] == n){ puts(\"-1\"); return; }\n\tif(p[1] == n) add(1, q[1], n);\n\telse if(p[1] != 1 && p[1] != 2){\n\t\tbool flag = 0;\n\t\trep(i, q[1] + 1, n){\n\t\t\tif(p[1] > p[i]){\n\t\t\t\tflag = 1;\n\t\t\t\tadd(1, q[1], i);\n\t\t\t\tbreak;\n\t\t\t}\n\t\t}\n\t\tif(!flag) add(1, q[2], n), add(1, q[1], q[2]);\n\t}\n\telse if(p[1] != 1){\n\t\tif(q[1] != 2){\t\t\t\n\t\t\tif(q[n] > q[1]) add(1, 2, q[n]);\n\t\t\tadd(1, q[n], q[1]); add(1, q[1], n);\n\t\t}\n\t\telse{\n\t\t\tint k = n; while(p[k] == k) --k;\n\t\t\tif(k != 2) add(1, 2, q[k]), add(1, 2, q[1]), add(1, q[1], k);\n\t\t\telse add(1, 3, n), add(1, 2, 3), add(1, 2, 3), add(1, 3, n);\n\t\t}\n\t}\n\tfor(int x = 2; x <= n; ++x){ if(p[x] == x) continue; add(1, x, q[x]); }\n\tif(cnt <= m){\n\t\tprintf(\"%d\\n\", cnt);\n\t\trep(i, 1, cnt) printf(\"%d %d %d\\n\", a[i], b[i], c[i]);\n\t}\n\telse puts(\"-1\");\n\trep(i, 1, cnt) a[i] = b[i] = c[i] = 0; cnt = 0;\n\treturn;\n}\nint main(){ int qwq = read(); while(qwq--) mian(); return 0; }\n```\n",
        "postTime": 1684149974,
        "uid": 147999,
        "name": "Warriors_Cat",
        "ccfLevel": 7,
        "title": "\u9898\u89e3 P9347\u3010\u4f3c\u66fe\u76f8\u8bc6\u71d5\u5f52\u6765\u3011"
    }
]